Workbook
Name \: #REF!
Name \: #REF!
Name \_JUNK: #N/A
Name \0: #N/A
Name \a: #REF!
Name \a: #REF!
Name \b: #REF!
Name \b: #REF!
Name \c: #REF!
Name \c: #REF!
Name \cac: #REF!
Name \d: #REF!
Name \da: #REF!
Name \dfhdtjht: #REF!
Name \e: #N/A
Name \f: #N/A
Name \fdfdr: #REF!
Name \fdfdr: #REF!
Name \FDWFDWF: #REF!
Name \FDWFDWF: #REF!
Name \g: #N/A
Name \h: #N/A
Name \hhh: #REF!
Name \hhh: #REF!
Name \I: #REF!
Name \I: #REF!
Name \iii: #REF!
Name \iii: #REF!
Name \J: #REF!
Name \K: #REF!
Name \ka: #REF!
Name \kkkk: #REF!
Name \l: #N/A
Name \lll: #REF!
Name \lll: #REF!
Name \M: #REF!
Name \M: #REF!
Name \ma: #REF!
Name \ma: #REF!
Name \N: #REF!
Name \na: #REF!
Name \O: #REF!
Name \p: #N/A
Name \pa: #REF!
Name \pa: #REF!
Name \par: #REF!
Name \par: #REF!
Name \pppp: #REF!
Name \pppp: #REF!
Name \Q: #N/A
Name \qa: #REF!
Name \qa: #REF!
Name \qaqa: #REF!
Name \qaqa: #REF!
Name \r: [69]MCMD95!$Q$121
Name \r: [70]MCMD95!$Q$121
Name \ra: #REF!
Name \ra: #REF!
Name \s: #N/A
Name \sasa: #REF!

Sheet ASSUMP.

Sheet Budget Plan
A1: PROJECT NAME | F1: Period | G1: 1 | H1: 2 | I1: 3 | J1: 4 | K1: 5 | L1: 6 | M1: 7 | N1: 8 | O1: 9 | P1: 10 | Q1: 11 | R1: 12 | S1: 13 | T1: 14 | U1: 15 | V1: 16 | W1: 17 | X1: 18 | Y1: 19 | Z1: 20 | AA1: 21 | AB1: 22 | AC1: 23 | AD1: 24 | AE1: 25 | AF1: 26 | AG1: 27 | AH1: 28 | AI1: 29 | AJ1: 30 | AK1: 31 | AL1: 32 | AM1: 33 | AN1: 34 | AO1: 35 | AP1: 36
F2: Year | G2: =YEAR(G3) -> 2019 | H2: =YEAR(H3) -> 2019 | I2: =YEAR(I3) -> 2019 | J2: =YEAR(J3) -> 2019 | K2: =YEAR(K3) -> 2019 | L2: =YEAR(L3) -> 2019 | M2: =YEAR(M3) -> 2019 | N2: =YEAR(N3) -> 2019 | ... AP2: =YEAR(AP3) -> 2022
F3: Month | G3: 43586 | H3: 43617 | I3: 43647 | J3: 43678 | K3: 43709 | L3: 43739 | M3: 43770 | N3: 43800 | O3: 43831 | P3: 43862 | Q3: 43891 | R3: 43922 | S3: 43952 | T3: 43983 | U3: 44013 | V3: 44044 | W3: 44075 | X3: 44105 | Y3: 44136 | Z3: 44166 | AA3: 44197 | AB3: 44228 | AC3: 44256 | AD3: 44287 | AE3: 44317 | AF3: 44348 | AG3: 44378 | AH3: 44409 | AI3: 44440 | AJ3: 44470 | AK3: 44501 | AL3: 44531 | AM3: 44562 | AN3: 44593 | AO3: 44621 | AP3: 44652
B4: YEAR 1 | C4: YEAR 2 | D4: YEAR 3 | E4: Assump. | AQ4: TOTAL | AR4: %
A5: Forecast
A6: PACKAGE A | F6: growth
A7: accumulate | G7: =G6 -> 0 | H7: =G7+H6 -> 0 | I7: =H7+I6 -> 0 | J7: =I7+J6 -> 0 | K7: =J7+K6 -> 0 | L7: =K7+L6 -> 0 | M7: =L7+M6 -> 0 | N7: =M7+N6 -> 0 | O7: =N7+O6 -> 0 | ... AP7: =AO7+AP6 -> 0
A8: PACKAGE B | F8: growth
A9: accumulate | G9: =G8 -> 0 | H9: =G9+H8 -> 0 | I9: =H9+I8 -> 0 | J9: =I9+J8 -> 0 | K9: =J9+K8 -> 0 | L9: =K9+L8 -> 0 | M9: =L9+M8 -> 0 | N9: =M9+N8 -> 0 | O9: =N9+O8 -> 0 | ... AP9: =AO9+AP8 -> 0
A10: PACKAGE C | F10: growth
A11: accumulate | G11: =G10 -> 0 | H11: =G11+H10 -> 0 | I11: =H11+I10 -> 0 | J11: =I11+J10 -> 0 | K11: =J11+K10 -> 0 | L11: =K11+L10 -> 0 | M11: =L11+M10 -> 0 | N11: =M11+N10 -> 0 | O11: =N11+O10 -> 0 | ... AP11: =AO11+AP10 -> 0
A19: P/L | AQ19: TOTAL | AR19: %
A20: Revenue | G20: =SUM(G21:G22) -> 0 | H20: =SUM(H21:H22) -> 0 | I20: =SUM(I21:I22) -> 0 | J20: =SUM(J21:J22) -> 0 | K20: =SUM(K21:K22) -> 0 | L20: =SUM(L21:L22) -> 0 | M20: =SUM(M21:M22) -> 0 | N20: =SUM(N21:N22) -> 0 | ... AP20: =SUM(AP21:AP22) -> 0 | AQ20: =SUM(G20:AP20) -> 0 | AR20: =AQ20/$AQ$20 -> #DIV/0!
A21: From INET (Develop Platform) | AQ21: =SUM(G21:AP21) -> 0 | AR21: =AQ21/$AQ$20 -> #DIV/0!
A22: Revenue From sales | G22: =SUM(G23:G27) -> 0 | H22: =SUM(H23:H27) -> 0 | I22: =SUM(I23:I27) -> 0 | J22: =SUM(J23:J27) -> 0 | K22: =SUM(K23:K27) -> 0 | L22: =SUM(L23:L27) -> 0 | M22: =SUM(M23:M27) -> 0 | N22: =SUM(N23:N27) -> 0 | ... AP22: =SUM(AP23:AP27) -> 0 | AQ22: =SUM(G22:AP22) -> 0 | AR22: =AQ22/$AQ$20 -> #DIV/0!
A23: PACKAGE A | F23: baht | G23: =$E$23*G7 -> 0 | H23: =$E$23*H7 -> 0 | I23: =$E$23*I7 -> 0 | J23: =$E$23*J7 -> 0 | K23: =$E$23*K7 -> 0 | L23: =$E$23*L7 -> 0 | M23: =$E$23*M7 -> 0 | N23: =$E$23*N7 -> 0 | ... AP23: =$E$23*AP7 -> 0 | AQ23: =SUM(G23:AP23) -> 0 | AR23: =AQ23/$AQ$20 -> #DIV/0!
A24: PACKAGE B | F24: baht | G24: =$E$24*G9 -> 0 | H24: =$E$24*H9 -> 0 | I24: =$E$24*I9 -> 0 | J24: =$E$24*J9 -> 0 | K24: =$E$24*K9 -> 0 | L24: =$E$24*L9 -> 0 | M24: =$E$24*M9 -> 0 | N24: =$E$24*N9 -> 0 | ... AP24: =$E$24*AP9 -> 0 | AQ24: =SUM(G24:AP24) -> 0 | AR24: =AQ24/$AQ$20 -> #DIV/0!
A25: PACKAGE C | F25: baht | G25: =$E$25*G11 -> 0 | H25: =$E$25*H11 -> 0 | I25: =$E$25*I11 -> 0 | J25: =$E$25*J11 -> 0 | K25: =$E$25*K11 -> 0 | L25: =$E$25*L11 -> 0 | M25: =$E$25*M11 -> 0 | N25: =$E$25*N11 -> 0 | ... AP25: =$E$25*AP11 -> 0 | AQ25: =SUM(G25:AP25) -> 0 | AR25: =AQ25/$AQ$20 -> #DIV/0!
AQ26: =SUM(G26:AP26) -> 0 | AR26: =AQ26/$AQ$20 -> #DIV/0!
AQ27: =SUM(G27:AP27) -> 0 | AR27: =AQ27/$AQ$20 -> #DIV/0!
A28: Direct Cost | G28: ='Infrastructure (Direct Cost)'!B31 -> 0 | H28: ='Infrastructure (Direct Cost)'!C31 -> 0 | I28: ='Infrastructure (Direct Cost)'!D31 -> 0 | J28: ='Infrastructure (Direct Cost)'!E31 -> 0 | K28: ='Infrastructure (Direct Cost)'!F31 -> 0 | L28: ='Infrastructure (Direct Cost)'!G31 -> 0 | M28: ='Infrastructure (Direct Cost)'!H31 -> 0 | N28: ='Infrastructure (Direct Cost)'!I31 -> 0 | ... R28: ='Infrastructure (Direct Cost)'!M31 -> 0 | S28: ='Infrastructure (Direct Cost)'!B32 -> 0 | T28: ='Infrastructure (Direct Cost)'!C32 -> 0 | U28: ='Infrastructure (Direct Cost)'!D32 -> 0 | V28: ='Infrastructure (Direct Cost)'!E32 -> 0 | W28: ='Infrastructure (Direct Cost)'!F32 -> 0 | X28: ='Infrastructure (Direct Cost)'!G32 -> 0 | Y28: ='Infrastructure (Direct Cost)'!H32 -> 0 | Z28: ='Infrastructure (Direct Cost)'!I32 -> 0 | ... AD28: ='Infrastructure (Direct Cost)'!M32 -> 0 | AE28: ='Infrastructure (Direct Cost)'!B33 -> 0 | AF28: ='Infrastructure (Direct Cost)'!C33 -> 0 | AG28: ='Infrastructure (Direct Cost)'!D33 -> 0 | AH28: ='Infrastructure (Direct Cost)'!E33 -> 0 | AI28: ='Infrastructure (Direct Cost)'!F33 -> 0 | AJ28: ='Infrastructure (Direct Cost)'!G33 -> 0 | AK28: ='Infrastructure (Direct Cost)'!H33 -> 0 | AL28: ='Infrastructure (Direct Cost)'!I33 -> 0 | ... AP28: ='Infrastructure (Direct Cost)'!M33 -> 0 | AQ28: =SUM(G28:AP28) -> 0 | AR28: =AQ28/$AQ$20 -> #DIV/0!
A29: Onetime | AQ29: =SUM(G29:AP29) -> 0 | AR29: =AQ29/$AQ$20 -> #DIV/0!
E30: Depreciation | F30: =5 -> 5 | AQ30: =SUM(G30:AP30) -> 0 | AR30: =AQ30/$AQ$20 -> #DIV/0!
E31: Depreciation | F31: =5 -> 5 | AQ31: =SUM(G31:AP31) -> 0 | AR31: =AQ31/$AQ$20 -> #DIV/0!
E32: Depreciation | F32: =5 -> 5 | AQ32: =SUM(G32:AP32) -> 0 | AR32: =AQ32/$AQ$20 -> #DIV/0!
E33: Depreciation | F33: =5 -> 5 | AQ33: =SUM(G33:AP33) -> 0 | AR33: =AQ33/$AQ$20 -> #DIV/0!
E34: Depreciation | F34: =5 -> 5 | AQ34: =SUM(G34:AP34) -> 0 | AR34: =AQ34/$AQ$20 -> #DIV/0!
E35: Depreciation | F35: =5 -> 5 | AQ35: =SUM(G35:AP35) -> 0 | AR35: =AQ35/$AQ$20 -> #DIV/0!
AQ36: =SUM(G36:AP36) -> 0 | AR36: =AQ36/$AQ$20 -> #DIV/0!
A37: Recurring | B37: Fix cost รายเดือน | AQ37: =SUM(G37:AP37) -> 0 | AR37: =AQ37/$AQ$20 -> #DIV/0!
A38: Cloud | AQ38: =SUM(G38:AP38) -> 0 | AR38: =AQ38/$AQ$20 -> #DIV/0!
AQ39: =SUM(G39:AP39) -> 0 | AR39: =AQ39/$AQ$20 -> #DIV/0!
AQ40: =SUM(G40:AP40) -> 0 | AR40: =AQ40/$AQ$20 -> #DIV/0!
AQ41: =SUM(G41:AP41) -> 0 | AR41: =AQ41/$AQ$20 -> #DIV/0!
A42: Pay Per Use | B42: ค่าใช้จ่ายผันแปร ตาม Forecast | AQ42: =SUM(G42:AP42) -> 0 | AR42: =AQ42/$AQ$20 -> #DIV/0!
AQ43: =SUM(G43:AP43) -> 0 | AR43: =AQ43/$AQ$20 -> #DIV/0!
AQ44: =SUM(G44:AP44) -> 0 | AR44: =AQ44/$AQ$20 -> #DIV/0!
AQ45: =SUM(G45:AP45) -> 0 | AR45: =AQ45/$AQ$20 -> #DIV/0!
A46: Operation | B46: เงินเดือน Engineer | G46: ='Developer (Direct Cost)'!C31 -> 0 | H46: ='Developer (Direct Cost)'!D31 -> 0 | I46: ='Developer (Direct Cost)'!E31 -> 0 | J46: ='Developer (Direct Cost)'!F31 -> 0 | K46: ='Developer (Direct Cost)'!G31 -> 0 | L46: ='Developer (Direct Cost)'!H31 -> 0 | M46: ='Developer (Direct Cost)'!I31 -> 0 | N46: ='Developer (Direct Cost)'!J31 -> 0 | ... R46: ='Developer (Direct Cost)'!N31 -> 0 | S46: ='Developer (Direct Cost)'!C32 -> 0 | T46: ='Developer (Direct Cost)'!D32 -> 0 | U46: ='Developer (Direct Cost)'!E32 -> 0 | V46: ='Developer (Direct Cost)'!F32 -> 0 | W46: ='Developer (Direct Cost)'!G32 -> 0 | X46: ='Developer (Direct Cost)'!H32 -> 0 | Y46: ='Developer (Direct Cost)'!I32 -> 0 | Z46: ='Developer (Direct Cost)'!J32 -> 0 | ... AD46: ='Developer (Direct Cost)'!N32 -> 0 | AE46: ='Infrastructure (Direct Cost)'!B33 -> 0 | AF46: ='Infrastructure (Direct Cost)'!C33 -> 0 | AG46: ='Infrastructure (Direct Cost)'!D33 -> 0 | AH46: ='Infrastructure (Direct Cost)'!E33 -> 0 | AI46: ='Infrastructure (Direct Cost)'!F33 -> 0 | AJ46: ='Infrastructure (Direct Cost)'!G33 -> 0 | AK46: ='Infrastructure (Direct Cost)'!H33 -> 0 | AL46: ='Infrastructure (Direct Cost)'!I33 -> 0 | ... AP46: ='Infrastructure (Direct Cost)'!M33 -> 0 | AQ46: =SUM(G46:AP46) -> 0 | AR46: =AQ46/$AQ$20 -> #DIV/0!
AQ47: =SUM(G47:AP47) -> 0 | AR47: =AQ47/$AQ$20 -> #DIV/0!
AQ48: =SUM(G48:AP48) -> 0 | AR48: =AQ48/$AQ$20 -> #DIV/0!
AQ49: =SUM(G49:AP49) -> 0 | AR49: =AQ49/$AQ$20 -> #DIV/0!
A50: Revenue Share | G50: =SUM(G51:G52) -> 0 | H50: =SUM(H51:H52) -> 0 | I50: =SUM(I51:I52) -> 0 | J50: =SUM(J51:J52) -> 0 | K50: =SUM(K51:K52) -> 0 | L50: =SUM(L51:L52) -> 0 | M50: =SUM(M51:M52) -> 0 | N50: =SUM(N51:N52) -> 0 | ... AP50: =SUM(AP51:AP52) -> 0 | AQ50: =SUM(G50:AP50) -> 0 | AR50: =AQ50/$AQ$20 -> #DIV/0!
A51: INET | E51: 0.1 | F51: from Rev | G51: =$E$51*G22 -> 0 | H51: =$E$51*H22 -> 0 | I51: =$E$51*I22 -> 0 | J51: =$E$51*J22 -> 0 | K51: =$E$51*K22 -> 0 | L51: =$E$51*L22 -> 0 | M51: =$E$51*M22 -> 0 | N51: =$E$51*N22 -> 0 | ... AP51: =$E$51*AP22 -> 0 | AQ51: =SUM(G51:AP51) -> 0 | AR51: =AQ51/$AQ$20 -> #DIV/0!
A52: Partner | E52: 0.1 | F52: from Rev | G52: =$E$51*G28 -> 0 | H52: =$E$51*H28 -> 0 | I52: =$E$51*I28 -> 0 | J52: =$E$51*J28 -> 0 | K52: =$E$51*K28 -> 0 | L52: =$E$51*L28 -> 0 | M52: =$E$51*M28 -> 0 | N52: =$E$51*N28 -> 0 | ... AP52: =$E$51*AP28 -> 0 | AQ52: =SUM(G52:AP52) -> 0 | AR52: =AQ52/$AQ$20 -> #DIV/0!
A53: Gross Profit | G53: =G20-G28-G50 -> 0 | H53: =H20-H28-H50 -> 0 | I53: =I20-I28-I50 -> 0 | J53: =J20-J28-J50 -> 0 | K53: =K20-K28-K50 -> 0 | L53: =L20-L28-L50 -> 0 | M53: =M20-M28-M50 -> 0 | N53: =N20-N28-N50 -> 0 | ... AP53: =AP20-AP28-AP50 -> 0 | AQ53: =SUM(G53:AP53) -> 0 | AR53: =AQ53/$AQ$20 -> #DIV/0!
A54: SG&A | G54: =SUM(G55:G65) -> #REF! | H54: =SUM(H55:H65) -> #REF! | I54: =SUM(I55:I65) -> #REF! | J54: =SUM(J55:J65) -> #REF! | K54: =SUM(K55:K65) -> #REF! | L54: =SUM(L55:L65) -> #REF! | M54: =SUM(M55:M65) -> #REF! | N54: =SUM(N55:N65) -> #REF! | ... AP54: =SUM(AP55:AP65) -> #REF! | AQ54: =SUM(G54:AP54) -> #REF! | AR54: =AQ54/$AQ$20 -> #REF!
A55: GM & officer | G55: ='Officer ( SGA) พนักงาน'!F139 -> 2000000 | H55: ='Officer ( SGA) พนักงาน'!G139 -> 2000000 | I55: ='Officer ( SGA) พนักงาน'!H139 -> 2000000 | J55: ='Officer ( SGA) พนักงาน'!I139 -> 2000000 | K55: ='Officer ( SGA) พนักงาน'!J139 -> 2000000 | L55: ='Officer ( SGA) พนักงาน'!K139 -> 2000000 | M55: ='Officer ( SGA) พนักงาน'!L139 -> 2000000 | N55: ='Officer ( SGA) พนักงาน'!M139 -> 2000000 | ... R55: ='Officer ( SGA) พนักงาน'!Q139 -> 2000000 | S55: ='Officer ( SGA) พนักงาน'!F140 -> 0 | T55: ='Officer ( SGA) พนักงาน'!G140 -> 0 | U55: ='Officer ( SGA) พนักงาน'!H140 -> 0 | V55: ='Officer ( SGA) พนักงาน'!I140 -> 0 | W55: ='Officer ( SGA) พนักงาน'!J140 -> 0 | X55: ='Officer ( SGA) พนักงาน'!K140 -> 0 | Y55: ='Officer ( SGA) พนักงาน'!L140 -> 0 | Z55: ='Officer ( SGA) พนักงาน'!M140 -> 0 | ... AD55: ='Officer ( SGA) พนักงาน'!Q140 -> 0 | AE55: ='Officer ( SGA) พนักงาน'!F141 -> 0 | AF55: ='Officer ( SGA) พนักงาน'!G141 -> 0 | AG55: ='Officer ( SGA) พนักงาน'!H141 -> 0 | AH55: ='Officer ( SGA) พนักงาน'!I141 -> 0 | AI55: ='Officer ( SGA) พนักงาน'!J141 -> 0 | AJ55: ='Officer ( SGA) พนักงาน'!K141 -> 0 | AK55: ='Officer ( SGA) พนักงาน'!L141 -> 0 | AL55: ='Officer ( SGA) พนักงาน'!M141 -> 0 | ... AP55: ='Officer ( SGA) พนักงาน'!Q141 -> 0 | AQ55: =SUM(G55:AP55) -> 24000000 | AR55: =AQ55/$AQ$20 -> #DIV/0!
A56: Rental Office | AQ56: =SUM(G56:AP56) -> 0 | AR56: =AQ56/$AQ$20 -> #DIV/0!
A57: Marketing | G57: ='Marketing (SGA)'!B56 -> #REF! | H57: ='Marketing (SGA)'!C56 -> #REF! | I57: ='Marketing (SGA)'!D56 -> #REF! | J57: ='Marketing (SGA)'!E56 -> #REF! | K57: ='Marketing (SGA)'!F56 -> #REF! | L57: ='Marketing (SGA)'!G56 -> #REF! | M57: ='Marketing (SGA)'!H56 -> #REF! | N57: ='Marketing (SGA)'!I56 -> #REF! | ... R57: ='Marketing (SGA)'!M56 -> #REF! | S57: ='Marketing (SGA)'!B57 -> #REF! | T57: ='Marketing (SGA)'!C57 -> #REF! | U57: ='Marketing (SGA)'!D57 -> #REF! | V57: ='Marketing (SGA)'!E57 -> #REF! | W57: ='Marketing (SGA)'!F57 -> #REF! | X57: ='Marketing (SGA)'!G57 -> #REF! | Y57: ='Marketing (SGA)'!H57 -> #REF! | Z57: ='Marketing (SGA)'!I57 -> #REF! | ... AD57: ='Marketing (SGA)'!M57 -> #REF! | AE57: ='Marketing (SGA)'!B58 -> #REF! | AF57: ='Marketing (SGA)'!C58 -> #REF! | AG57: ='Marketing (SGA)'!D58 -> #REF! | AH57: ='Marketing (SGA)'!E58 -> #REF! | AI57: ='Marketing (SGA)'!F58 -> #REF! | AJ57: ='Marketing (SGA)'!G58 -> #REF! | AK57: ='Marketing (SGA)'!H58 -> #REF! | AL57: ='Marketing (SGA)'!I58 -> #REF! | ... AP57: ='Marketing (SGA)'!M58 -> #REF! | AQ57: =SUM(G57:AP57) -> #REF! | AR57: =AQ57/$AQ$20 -> #REF!
A58: Trainning | AQ58: =SUM(G58:AP58) -> 0 | AR58: =AQ58/$AQ$20 -> #DIV/0!
A59: Other Expense | G59: ='Other Expense (SGA)'!B32 -> 0 | H59: ='Other Expense (SGA)'!C32 -> 0 | I59: ='Other Expense (SGA)'!D32 -> 0 | J59: ='Other Expense (SGA)'!E32 -> 0 | K59: ='Other Expense (SGA)'!F32 -> 0 | L59: ='Other Expense (SGA)'!G32 -> 0 | M59: ='Other Expense (SGA)'!H32 -> 0 | N59: ='Other Expense (SGA)'!I32 -> 0 | ... R59: ='Other Expense (SGA)'!M32 -> 0 | S59: ='Other Expense (SGA)'!B33 -> 0 | T59: ='Other Expense (SGA)'!C33 -> 0 | U59: ='Other Expense (SGA)'!D33 -> 0 | V59: ='Other Expense (SGA)'!E33 -> 0 | W59: ='Other Expense (SGA)'!F33 -> 0 | X59: ='Other Expense (SGA)'!G33 -> 0 | Y59: ='Other Expense (SGA)'!H33 -> 0 | Z59: ='Other Expense (SGA)'!I33 -> 0 | ... AD59: ='Other Expense (SGA)'!M33 -> 0 | AE59: ='Other Expense (SGA)'!B34 -> 0 | AF59: ='Other Expense (SGA)'!C34 -> 0 | AG59: ='Other Expense (SGA)'!D34 -> 0 | AH59: ='Other Expense (SGA)'!E34 -> 0 | AI59: ='Other Expense (SGA)'!F34 -> 0 | AJ59: ='Other Expense (SGA)'!G34 -> 0 | AK59: ='Other Expense (SGA)'!H34 -> 0 | AL59: ='Other Expense (SGA)'!I34 -> 0 | ... AP59: ='Other Expense (SGA)'!M34 -> 0 | AQ59: =SUM(G59:AP59) -> 0 | AR59: =AQ59/$AQ$20 -> #DIV/0!
A60: Board | AQ60: =SUM(G60:AP60) -> 0 | AR60: =AQ60/$AQ$20 -> #DIV/0!
A61: Account & Finance | F61: per month | G61: =$E$61 -> 0 | H61: =$E$61 -> 0 | I61: =$E$61 -> 0 | J61: =$E$61 -> 0 | K61: =$E$61 -> 0 | L61: =$E$61 -> 0 | M61: =$E$61 -> 0 | N61: =$E$61 -> 0 | ... AP61: =$E$61 -> 0 | AQ61: =SUM(G61:AP61) -> 0 | AR61: =AQ61/$AQ$20 -> #DIV/0!
AQ62: =SUM(G62:AP62) -> 0 | AR62: =AQ62/$AQ$20 -> #DIV/0!
AQ63: =SUM(G63:AP63) -> 0 | AR63: =AQ63/$AQ$20 -> #DIV/0!
AQ65: =SUM(G65:AP65) -> 0 | AR65: =AQ65/$AQ$20 -> #DIV/0!
AQ66: =SUM(G66:AP66) -> 0 | AR66: =AQ66/$AQ$20 -> #DIV/0!
AQ67: =SUM(G67:AP67) -> 0 | AR67: =AQ67/$AQ$20 -> #DIV/0!
AQ68: =SUM(G68:AP68) -> 0 | AR68: =AQ68/$AQ$20 -> #DIV/0!
A70: EBIT | G70: =G53-G54 -> #REF! | H70: =H53-H54 -> #REF! | I70: =I53-I54 -> #REF! | J70: =J53-J54 -> #REF! | K70: =K53-K54 -> #REF! | L70: =L53-L54 -> #REF! | M70: =M53-M54 -> #REF! | N70: =N53-N54 -> #REF! | ... AP70: =AP53-AP54 -> #REF! | AQ70: =SUM(G70:AP70) -> #REF! | AR70: =AQ70/$AQ$20 -> #REF!
A71: Interest | G71: 0 | H71: 0 | I71: 0 | J71: 0 | K71: 0 | L71: 0 | M71: 0 | N71: 0 | O71: 0 | P71: 0 | Q71: 0 | R71: 0 | S71: 0 | T71: 0 | U71: 0 | V71: 0 | W71: 0 | X71: 0 | Y71: 0 | Z71: 0 | AA71: 0 | AB71: 0 | AC71: 0 | AD71: 0 | AE71: 0 | AF71: 0 | AG71: 0 | AH71: 0 | AI71: 0 | AJ71: 0 | AK71: 0 | AL71: 0 | AM71: 0 | AN71: 0 | AO71: 0 | AP71: 0 | AQ71: =SUM(G71:AP71) -> 0 | AR71: =AQ71/$AQ$20 -> #DIV/0!
A72: Loan | G72: 0 | H72: 0 | I72: 0 | J72: 0 | K72: 0 | L72: 0 | M72: 0 | N72: 0 | O72: 0 | P72: 0 | Q72: 0 | R72: 0 | S72: 0 | T72: 0 | U72: 0 | V72: 0 | W72: 0 | X72: 0 | Y72: 0 | Z72: 0 | AA72: 0 | AB72: 0 | AC72: 0 | AD72: 0 | AE72: 0 | AF72: 0 | AG72: 0 | AH72: 0 | AI72: 0 | AJ72: 0 | AK72: 0 | AL72: 0 | AM72: 0 | AN72: 0 | AO72: 0 | AP72: 0 | AQ72: =SUM(G72:AP72) -> 0 | AR72: =AQ72/$AQ$20 -> #DIV/0!
A73: Leasing | G73: 0 | H73: 0 | I73: 0 | J73: 0 | K73: 0 | L73: 0 | M73: 0 | N73: 0 | O73: 0 | P73: 0 | Q73: 0 | R73: 0 | S73: 0 | T73: 0 | U73: 0 | V73: 0 | W73: 0 | X73: 0 | Y73: 0 | Z73: 0 | AA73: 0 | AB73: 0 | AC73: 0 | AD73: 0 | AE73: 0 | AF73: 0 | AG73: 0 | AH73: 0 | AI73: 0 | AJ73: 0 | AK73: 0 | AL73: 0 | AM73: 0 | AN73: 0 | AO73: 0 | AP73: 0 | AQ73: =SUM(G73:AP73) -> 0 | AR73: =AQ73/$AQ$20 -> #DIV/0!
A74: EBT | G74: =G70-SUM(G71:G73) -> #REF! | H74: =H70-SUM(H71:H73) -> #REF! | I74: =I70-SUM(I71:I73) -> #REF! | J74: =J70-SUM(J71:J73) -> #REF! | K74: =K70-SUM(K71:K73) -> #REF! | L74: =L70-SUM(L71:L73) -> #REF! | M74: =M70-SUM(M71:M73) -> #REF! | N74: =N70-SUM(N71:N73) -> #REF! | ... AP74: =AP70-SUM(AP71:AP73) -> #REF! | AQ74: =SUM(G74:AP74) -> #REF! | AR74: =AQ74/$AQ$20 -> #REF!
A75: Tax | G75: 0 | H75: 0 | I75: 0 | J75: 0 | K75: 0 | L75: 0 | M75: 0 | N75: 0 | O75: 0 | P75: 0 | Q75: 0 | R75: 0 | S75: 0 | T75: 0 | U75: 0 | V75: 0 | W75: 0 | X75: 0 | Y75: 0 | Z75: 0 | AA75: 0 | AB75: 0 | AC75: 0 | AD75: 0 | AE75: 0 | AF75: 0 | AG75: 0 | AH75: 0 | AI75: 0 | AJ75: 0 | AK75: 0 | AL75: 0 | AM75: 0 | AN75: 0 | AO75: 0 | AP75: 0 | AQ75: =SUM(G75:AP75) -> 0 | AR75: =AQ75/$AQ$20 -> #DIV/0!
A76: Net Profit | G76: =G74-G75 -> #REF! | H76: =H74-H75 -> #REF! | I76: =I74-I75 -> #REF! | J76: =J74-J75 -> #REF! | K76: =K74-K75 -> #REF! | L76: =L74-L75 -> #REF! | M76: =M74-M75 -> #REF! | N76: =N74-N75 -> #REF! | ... AP76: =AP74-AP75 -> #REF! | AQ76: =SUM(G76:AP76) -> #REF! | AR76: =AQ76/$AQ$20 -> #REF!
A77: RE | G77: =G76 -> #REF! | H77: =H76 -> #REF! | I77: =H77+I76 -> #REF! | J77: =I77+J76 -> #REF! | K77: =J77+K76 -> #REF! | L77: =K77+L76 -> #REF! | M77: =L77+M76 -> #REF! | N77: =M77+N76 -> #REF! | O77: =N77+O76 -> #REF! | P77: =O77+P76 -> #REF! | Q77: =P77+Q76 -> #REF! | R77: =G77+R76 -> #REF! | S77: =H77+S76 -> #REF! | T77: =S77+T76 -> #REF! | U77: =T77+U76 -> #REF! | V77: =U77+V76 -> #REF! | W77: =V77+W76 -> #REF! | X77: =W77+X76 -> #REF! | Y77: =X77+Y76 -> #REF! | Z77: =Y77+Z76 -> #REF! | AA77: =Z77+AA76 -> #REF! | ... AP77: =AO77+AP76 -> #REF!
A78: C/F | AQ78: TOTAL
A79: Cash In | G79: =SUM(G80:G82) -> 0 | H79: =SUM(H80:H82) -> 0 | I79: =SUM(I80:I82) -> 0 | J79: =SUM(J80:J82) -> 0 | K79: =SUM(K80:K82) -> 0 | L79: =SUM(L80:L82) -> 0 | M79: =SUM(M80:M82) -> 0 | N79: =SUM(N80:N82) -> 0 | ... AP79: =SUM(AP80:AP82) -> 0 | AQ79: =SUM(G79:AP79) -> 0 | AR79: =AQ79/$AQ$79 -> #DIV/0!
A80: From INET (Develop Platform) | G80: =G21 -> 0 | H80: =H21 -> 0 | I80: =I21 -> 0 | J80: =J21 -> 0 | K80: =K21 -> 0 | L80: =L21 -> 0 | M80: =M21 -> 0 | N80: =N21 -> 0 | ... AP80: =AP21 -> 0 | AQ80: =SUM(G80:AP80) -> 0 | AR80: =AQ80/$AQ$79 -> #DIV/0!
A81: Revenue From sales | H81: =H22 -> 0 | I81: =I22 -> 0 | J81: =J22 -> 0 | K81: =K22 -> 0 | L81: =L22 -> 0 | M81: =M22 -> 0 | N81: =N22 -> 0 | O81: =O22 -> 0 | ... Q81: =Q22 -> 0 | R81: =G22 -> 0 | S81: =H22 -> 0 | T81: =I22 -> 0 | U81: =J22 -> 0 | V81: =K22 -> 0 | W81: =L22 -> 0 | X81: =M22 -> 0 | Y81: =N22 -> 0 | ... AP81: =AE22 -> 0 | AQ81: =SUM(G81:AP81) -> 0 | AR81: =AQ81/$AQ$79 -> #DIV/0!
AQ82: =SUM(G82:AP82) -> 0 | AR82: =AQ82/$AQ$79 -> #DIV/0!
A83: Cash Out | G83: =SUM(G85,G88,,G93,G94,G95,G92) -> #REF! | H83: =SUM(H85,H88,,H93,H94,H95,H92) -> #REF! | I83: =SUM(I85,I88,,I93,I94,I95,I92) -> #REF! | J83: =SUM(J85,J88,,J93,J94,J95,J92) -> #REF! | K83: =SUM(K85,K88,,K93,K94,K95,K92) -> #REF! | L83: =SUM(L85,L88,,L93,L94,L95,L92) -> #REF! | M83: =SUM(M85,M88,,M93,M94,M95,M92) -> #REF! | N83: =SUM(N85,N88,,N93,N94,N95,N92) -> #REF! | ... AP83: =SUM(AP85,AP88,,AP93,AP94,AP95,AP92) -> #REF! | AQ83: =SUM(G83:AP83) -> #REF! | AR83: =AQ83/$AQ$79 -> #REF!
A84: Direct Cost | G84: =SUM(G85,G88) -> 0 | H84: =SUM(H85,H88) -> 0 | I84: =SUM(I85,I88) -> 0 | J84: =SUM(J85,J88) -> 0 | K84: =SUM(K85,K88) -> 0 | L84: =SUM(L85,L88) -> 0 | M84: =SUM(M85,M88) -> 0 | N84: =SUM(N85,N88) -> 0 | ... AP84: =SUM(AP85,AP88) -> 0 | AQ84: =SUM(G84:AP84) -> 0 | AR84: =AQ84/$AQ$79 -> #DIV/0!
A85: One Time | G85: =SUM(G86:G87) -> 0 | H85: =SUM(H86:H87) -> 0 | I85: =SUM(I86:I87) -> 0 | J85: =SUM(J86:J87) -> 0 | K85: =SUM(K86:K87) -> 0 | L85: =SUM(L86:L87) -> 0 | M85: =SUM(M86:M87) -> 0 | N85: =SUM(N86:N87) -> 0 | ... AP85: =SUM(AP86:AP87) -> 0 | AQ85: =SUM(G85:AP85) -> 0 | AR85: =AQ85/$AQ$79 -> #DIV/0!
AQ86: =SUM(G86:AP86) -> 0 | AR86: =AQ86/$AQ$79 -> #DIV/0!
G87: ='Infrastructure (Direct Cost)'!B13 -> 0 | AQ87: =SUM(G87:AP87) -> 0 | AR87: =AQ87/$AQ$79 -> #DIV/0!
A88: Recurring | G88: =SUM(G89:G91) -> 0 | H88: =SUM(H89:H91) -> 0 | I88: =SUM(I89:I91) -> 0 | J88: =SUM(J89:J91) -> 0 | K88: =SUM(K89:K91) -> 0 | L88: =SUM(L89:L91) -> 0 | M88: =SUM(M89:M91) -> 0 | N88: =SUM(N89:N91) -> 0 | ... AP88: =SUM(AP89:AP91) -> 0 | AQ88: =SUM(G88:AP88) -> 0 | AR88: =AQ88/$AQ$79 -> #DIV/0!
H89: =G34 -> 0 | I89: =H34 -> 0 | J89: =I34 -> 0 | K89: =J34 -> 0 | L89: =K34 -> 0 | M89: =L34 -> 0 | N89: =M34 -> 0 | O89: =N34 -> 0 | ... AP89: =AO34 -> 0 | AQ89: =SUM(G89:AP89) -> 0 | AR89: =AQ89/$AQ$79 -> #DIV/0!
H90: =G36 -> 0 | I90: =H36 -> 0 | J90: =I36 -> 0 | K90: =J36 -> 0 | L90: =K36 -> 0 | M90: =L36 -> 0 | N90: =M36 -> 0 | O90: =N36 -> 0 | ... AP90: =AO36 -> 0 | AQ90: =SUM(G90:AP90) -> 0 | AR90: =AQ90/$AQ$79 -> #DIV/0!
G91: =G45 -> 0 | H91: =H45 -> 0 | I91: =I45 -> 0 | J91: =J45 -> 0 | K91: =K45 -> 0 | L91: =L45 -> 0 | M91: =M45 -> 0 | N91: =N45 -> 0 | ... AP91: =AP45 -> 0 | AQ91: =SUM(G91:AP91) -> 0 | AR91: =AQ91/$AQ$79 -> #DIV/0!
A92: Revshare | H92: =G50 -> 0 | I92: =H50 -> 0 | J92: =I50 -> 0 | K92: =J50 -> 0 | L92: =K50 -> 0 | M92: =L50 -> 0 | N92: =M50 -> 0 | O92: =N50 -> 0 | ... AP92: =AO50 -> 0 | AQ92: =SUM(G92:AP92) -> 0 | AR92: =AQ92/$AQ$79 -> #DIV/0!
A93: SG&A | G93: =G54 -> #REF! | H93: =H54 -> #REF! | I93: =I54 -> #REF! | J93: =J54 -> #REF! | K93: =K54 -> #REF! | L93: =L54 -> #REF! | M93: =M54 -> #REF! | N93: =N54 -> #REF! | ... AP93: =AP54 -> #REF! | AQ93: =SUM(G93:AP93) -> #REF! | AR93: =AQ93/$AQ$79 -> #REF!
A94: Interest | G94: 0 | H94: 0 | I94: 0 | J94: 0 | K94: 0 | L94: 0 | M94: 0 | N94: 0 | O94: 0 | P94: 0 | Q94: 0 | R94: 0 | S94: 0 | T94: 0 | U94: 0 | V94: 0 | W94: 0 | X94: 0 | Y94: 0 | Z94: 0 | AA94: 0 | AB94: 0 | AC94: 0 | AD94: 0 | AE94: 0 | AF94: 0 | AG94: 0 | AH94: 0 | AI94: 0 | AJ94: 0 | AK94: 0 | AL94: 0 | AM94: 0 | AN94: 0 | AO94: 0 | AP94: 0 | AQ94: =SUM(G94:AP94) -> 0 | AR94: =AQ94/$AQ$79 -> #DIV/0!
A95: Tax | G95: 0 | H95: 0 | I95: 0 | J95: 0 | K95: 0 | L95: 0 | M95: 0 | N95: 0 | O95: 0 | P95: 0 | Q95: 0 | R95: 0 | S95: 0 | T95: 0 | U95: 0 | V95: 0 | W95: 0 | X95: 0 | Y95: 0 | Z95: 0 | AA95: 0 | AB95: 0 | AC95: 0 | AD95: 0 | AE95: 0 | AF95: 0 | AG95: 0 | AH95: 0 | AI95: 0 | AJ95: 0 | AK95: 0 | AL95: 0 | AM95: 0 | AN95: 0 | AO95: 0 | AP95: 0 | AQ95: =SUM(G95:AP95) -> 0 | AR95: =AQ95/$AQ$79 -> #DIV/0!
A96: Net Cash | G96: =G79-G83 -> #REF! | H96: =H79-H83 -> #REF! | I96: =I79-I83 -> #REF! | J96: =J79-J83 -> #REF! | K96: =K79-K83 -> #REF! | L96: =L79-L83 -> #REF! | M96: =M79-M83 -> #REF! | N96: =N79-N83 -> #REF! | ... AP96: =AP79-AP83 -> #REF! | AQ96: =SUM(G96:AP96) -> #REF! | AR96: =AQ96/$AQ$79 -> #REF!
A97: Cash BF (ยกมา) | H97: =G98 -> #REF! | I97: =H98 -> #REF! | J97: =I98 -> #REF! | K97: =J98 -> #REF! | L97: =K98 -> #REF! | M97: =L98 -> #REF! | N97: =M98 -> #REF! | O97: =N98 -> #REF! | ... AP97: =AO98 -> #REF!
A98: Cash CF (ยกไป) | G98: =G96 -> #REF! | H98: =H96+H97 -> #REF! | I98: =I96+I97 -> #REF! | J98: =J96+J97 -> #REF! | K98: =K96+K97 -> #REF! | L98: =L96+L97 -> #REF! | M98: =M96+M97 -> #REF! | N98: =N96+N97 -> #REF! | O98: =O96+O97 -> #REF! | ... AP98: =AP96+AP97 -> #REF!
A100: ROI | B100: =AQ96/AQ83 -> #REF!
A101: PB on | B101: =(MATCH(0,F98:AP98)-1)+(0-INDEX(F98:AP98,MATCH(0,F98:AP98)))/(INDEX(F98:AP98,MATCH(0,F98:AP98)+1)-INDEX(F98:AP98,MATCH(0,F98:AP98))) -> #N/A
A102: PB on month | B102: =IFERROR(HLOOKUP(ROUNDUP(B101,0),$G$1:$AO$12,3),"Non PB") -> Non PB
A103: IRR | B103: =IRR(G96:AP96) -> #VALUE!
A104: B.E.P on | B104: =(MATCH(0,F76:AP76)-1)+(0-INDEX(F76:AP76,MATCH(0,F76:AP76)))/(INDEX(F76:AP76,MATCH(0,F76:AP76)+1)-INDEX(F76:AP76,MATCH(0,F76:AP76))) -> #N/A
A105: B.E.P on Month | B105: =IFERROR(HLOOKUP(ROUNDUP(B104,0),$G$1:$AO$12,3),"Non B.E.P") -> Non B.E.P
A106: B.E.P Amount | B106: =IFERROR(HLOOKUP(ROUNDUP(B105,0),$G$3:$AP$22,11),"Non B.E.P") -> Non B.E.P
A107: B.E.P Unit | B107: =IFERROR(HLOOKUP(ROUNDUP(B105,0),$G$3:$AP$22,9),"None") -> None
A108: RE | B108: =(MATCH(0,F77:AP77)-1)+(0-INDEX(F77:AP77,MATCH(0,F77:AP77)))/(INDEX(F77:AP77,MATCH(0,F77:AP77)+1)-INDEX(F77:AP77,MATCH(0,F77:AP77))) -> #N/A
A109: RE on Month | B109: =IFERROR(HLOOKUP(ROUNDUP(B108,0),$G$1:$AP$3,3),"None") -> None
A110: NPV | B110: =NPV(B111,G96:AP96) -> #REF!
...

Sheet REVENUE
A1: Forecast & Revenue
A2: Year1
A3: CATEGORY | E3: 44197 | G3: 44228 | I3: 44256 | K3: 44287 | M3: 44317 | O3: 44348 | Q3: 44378 | S3: 44409 | U3: 44440 | W3: 44470 | Y3: 44501 | AA3: 44531 | AB3: Total
A5: Project
A6: Ads
A7: xxxx
A10: Design Project condo | B10: 26 | C10: 850 | D10: 0 | E10: =(B10*C10)*D10 -> 0 | F10: 0 | G10: =(B10*C10)*F10 -> 0 | H10: 0 | I10: =(B10*C10)*H10 -> 0 | J10: 0 | K10: =(B10*C10)*J10 -> 0 | L10: 0 | M10: =(B10*C10)*L10 -> 0 | N10: 0 | O10: =(B10*C10)*N10 -> 0 | P10: 10 | Q10: =(B10*C10)*P10 -> 221000 | R10: 10 | S10: =(B10*C10)*R10 -> 221000 | T10: 10 | U10: =(B10*C10)*T10 -> 221000 | V10: 10 | W10: =(B10*C10)*V10 -> 221000 | X10: 10 | Y10: =(B10*C10)*X10 -> 221000 | Z10: 10 | AA10: =(B10*C10)*Z10 -> 221000
A11: Design Project condo | B11: 33 | C11: 850 | D11: 0 | E11: =(B11*C11)*D11 -> 0 | F11: 0 | G11: =(B11*C11)*F11 -> 0 | H11: 0 | I11: =(B11*C11)*H11 -> 0 | J11: 0 | K11: =(B11*C11)*J11 -> 0 | L11: 0 | M11: =(B11*C11)*L11 -> 0 | N11: 0 | O11: =(B11*C11)*N11 -> 0 | P11: 5 | Q11: =(B11*C11)*P11 -> 140250 | R11: 5 | S11: =(B11*C11)*R11 -> 140250 | T11: 5 | U11: =(B11*C11)*T11 -> 140250 | V11: 5 | W11: =(B11*C11)*V11 -> 140250 | X11: 5 | Y11: =(B11*C11)*X11 -> 140250 | Z11: 5 | AA11: =(B11*C11)*Z11 -> 140250
A12: Design Project condo | B12: 64 | C12: 850 | D12: 0 | E12: =(B12*C12)*D12 -> 0 | F12: 0 | G12: =(B12*C12)*F12 -> 0 | H12: 0 | I12: =(B12*C12)*H12 -> 0 | J12: 0 | K12: =(B12*C12)*J12 -> 0 | L12: 0 | M12: =(B12*C12)*L12 -> 0 | N12: 0 | O12: =(B12*C12)*N12 -> 0 | P12: 2 | Q12: =(B12*C12)*P12 -> 108800 | R12: 2 | S12: =(B12*C12)*R12 -> 108800 | T12: 2 | U12: =(B12*C12)*T12 -> 108800 | V12: 2 | W12: =(B12*C12)*V12 -> 108800 | X12: 2 | Y12: =(B12*C12)*X12 -> 108800 | Z12: 2 | AA12: =(B12*C12)*Z12 -> 108800
A13: Design Project condo | B13: 100 | C13: 850 | D13: 0 | E13: =(B13*C13)*D13 -> 0 | F13: 0 | G13: =(B13*C13)*F13 -> 0 | H13: 0 | I13: =(B13*C13)*H13 -> 0 | J13: 0 | K13: =(B13*C13)*J13 -> 0 | L13: 0 | M13: =(B13*C13)*L13 -> 0 | N13: 0 | O13: =(B13*C13)*N13 -> 0 | P13: 0 | Q13: =(B13*C13)*P13 -> 0 | R13: 0 | S13: =(B13*C13)*R13 -> 0 | T13: 0 | U13: =(B13*C13)*T13 -> 0 | V13: 0 | W13: =(B13*C13)*V13 -> 0 | X13: 0 | Y13: =(B13*C13)*X13 -> 0 | Z13: 0 | AA13: =(B13*C13)*Z13 -> 0
K14: =(B14*C14)*J14 -> 0 | M14: =(B14*C14)*L14 -> 0 | O14: =(B14*C14)*N14 -> 0 | Q14: =(B14*C14)*P14 -> 0 | S14: =(B14*C14)*R14 -> 0 | U14: =(B14*C14)*T14 -> 0 | W14: =(B14*C14)*V14 -> 0 | Y14: =(B14*C14)*X14 -> 0 | AA14: =(B14*C14)*Z14 -> 0
A15: Design Project House | B15: 150 | C15: 850 | D15: 0 | E15: =(B15*C15)*D15 -> 0 | F15: 0 | G15: =(B15*C15)*F15 -> 0 | H15: 0 | I15: =(B15*C15)*H15 -> 0 | J15: 0 | K15: =(B15*C15)*J15 -> 0 | L15: 0 | M15: =(B15*C15)*L15 -> 0 | N15: 0 | O15: =(B15*C15)*N15 -> 0 | P15: 10 | Q15: =(B15*C15)*P15 -> 1275000 | R15: 10 | S15: =(B15*C15)*R15 -> 1275000 | T15: 10 | U15: =(B15*C15)*T15 -> 1275000 | V15: 10 | W15: =(B15*C15)*V15 -> 1275000 | X15: 10 | Y15: =(B15*C15)*X15 -> 1275000 | Z15: 10 | AA15: =(B15*C15)*Z15 -> 1275000
A16: Design Project House | B16: 250 | C16: 850 | D16: 0 | E16: =(B16*C16)*D16 -> 0 | F16: 0 | G16: =(B16*C16)*F16 -> 0 | H16: 0 | I16: =(B16*C16)*H16 -> 0 | J16: 0 | K16: =(B16*C16)*J16 -> 0 | L16: 0 | M16: =(B16*C16)*L16 -> 0 | N16: 0 | O16: =(B16*C16)*N16 -> 0 | P16: 5 | Q16: =(B16*C16)*P16 -> 1062500 | R16: 5 | S16: =(B16*C16)*R16 -> 1062500 | T16: 5 | U16: =(B16*C16)*T16 -> 1062500 | V16: 5 | W16: =(B16*C16)*V16 -> 1062500 | X16: 5 | Y16: =(B16*C16)*X16 -> 1062500 | Z16: 5 | AA16: =(B16*C16)*Z16 -> 1062500
A17: Design Project House | B17: 350 | C17: 850 | D17: 0 | E17: =(B17*C17)*D17 -> 0 | F17: 0 | G17: =(B17*C17)*F17 -> 0 | H17: 0 | I17: =(B17*C17)*H17 -> 0 | J17: 0 | K17: =(B17*C17)*J17 -> 0 | L17: 0 | M17: =(B17*C17)*L17 -> 0 | N17: 0 | O17: =(B17*C17)*N17 -> 0 | P17: 2 | Q17: =(B17*C17)*P17 -> 595000 | R17: 2 | S17: =(B17*C17)*R17 -> 595000 | T17: 2 | U17: =(B17*C17)*T17 -> 595000 | V17: 2 | W17: =(B17*C17)*V17 -> 595000 | X17: 2 | Y17: =(B17*C17)*X17 -> 595000 | Z17: 2 | AA17: =(B17*C17)*Z17 -> 595000
A18: Design Project House | B18: 500 | C18: 850 | D18: 0 | E18: =(B18*C18)*D18 -> 0 | F18: 0 | G18: =(B18*C18)*F18 -> 0 | H18: 0 | I18: =(B18*C18)*H18 -> 0 | J18: 0 | K18: =(B18*C18)*J18 -> 0 | L18: 0 | M18: =(B18*C18)*L18 -> 0 | N18: 0 | O18: =(B18*C18)*N18 -> 0 | P18: 0 | Q18: =(B18*C18)*P18 -> 0 | R18: 0 | S18: =(B18*C18)*R18 -> 0 | T18: 0 | U18: =(B18*C18)*T18 -> 0 | V18: 0 | W18: =(B18*C18)*V18 -> 0 | X18: 0 | Y18: =(B18*C18)*X18 -> 0 | Z18: 0 | AA18: =(B18*C18)*Z18 -> 0
K19: =(B19*C19)*J19 -> 0 | M19: =(B19*C19)*L19 -> 0 | O19: =(B19*C19)*N19 -> 0 | Q19: =(B19*C19)*P19 -> 0 | S19: =(B19*C19)*R19 -> 0 | U19: =(B19*C19)*T19 -> 0 | W19: =(B19*C19)*V19 -> 0 | Y19: =(B19*C19)*X19 -> 0 | AA19: =(B19*C19)*Z19 -> 0
A20: Design Project Shop | B20: 100 | C20: 850 | D20: 0 | E20: =(B20*C20)*D20 -> 0 | F20: 0 | G20: =(B20*C20)*F20 -> 0 | H20: 0 | I20: =(B20*C20)*H20 -> 0 | J20: 0 | K20: =(B20*C20)*J20 -> 0 | L20: 0 | M20: =(B20*C20)*L20 -> 0 | N20: 0 | O20: =(B20*C20)*N20 -> 0 | P20: 5 | Q20: =(B20*C20)*P20 -> 425000 | R20: 5 | S20: =(B20*C20)*R20 -> 425000 | T20: 5 | U20: =(B20*C20)*T20 -> 425000 | V20: 5 | W20: =(B20*C20)*V20 -> 425000 | X20: 5 | Y20: =(B20*C20)*X20 -> 425000 | Z20: 5 | AA20: =(B20*C20)*Z20 -> 425000
A21: Design Project Shop | B21: 150 | C21: 850 | D21: 0 | E21: =(B21*C21)*D21 -> 0 | F21: 0 | G21: =(B21*C21)*F21 -> 0 | H21: 0 | I21: =(B21*C21)*H21 -> 0 | J21: 0 | K21: =(B21*C21)*J21 -> 0 | L21: 0 | M21: =(B21*C21)*L21 -> 0 | N21: 0 | O21: =(B21*C21)*N21 -> 0 | P21: 4 | Q21: =(B21*C21)*P21 -> 510000 | R21: 4 | S21: =(B21*C21)*R21 -> 510000 | T21: 4 | U21: =(B21*C21)*T21 -> 510000 | V21: 4 | W21: =(B21*C21)*V21 -> 510000 | X21: 4 | Y21: =(B21*C21)*X21 -> 510000 | Z21: 4 | AA21: =(B21*C21)*Z21 -> 510000
A22: Design Project Shop | B22: 250 | C22: 850 | D22: 0 | E22: =(B22*C22)*D22 -> 0 | F22: 0 | G22: =(B22*C22)*F22 -> 0 | H22: 0 | I22: =(B22*C22)*H22 -> 0 | J22: 0 | K22: =(B22*C22)*J22 -> 0 | L22: 0 | M22: =(B22*C22)*L22 -> 0 | N22: 0 | O22: =(B22*C22)*N22 -> 0 | P22: 3 | Q22: =(B22*C22)*P22 -> 637500 | R22: 3 | S22: =(B22*C22)*R22 -> 637500 | T22: 3 | U22: =(B22*C22)*T22 -> 637500 | V22: 3 | W22: =(B22*C22)*V22 -> 637500 | X22: 3 | Y22: =(B22*C22)*X22 -> 637500 | Z22: 3 | AA22: =(B22*C22)*Z22 -> 637500
A23: Design Project Shop | B23: 350 | C23: 850 | D23: 0 | E23: =(B23*C23)*D23 -> 0 | F23: 0 | G23: =(B23*C23)*F23 -> 0 | H23: 0 | I23: =(B23*C23)*H23 -> 0 | J23: 0 | K23: =(B23*C23)*J23 -> 0 | L23: 0 | M23: =(B23*C23)*L23 -> 0 | N23: 0 | O23: =(B23*C23)*N23 -> 0 | P23: 3 | Q23: =(B23*C23)*P23 -> 892500 | R23: 3 | S23: =(B23*C23)*R23 -> 892500 | T23: 3 | U23: =(B23*C23)*T23 -> 892500 | V23: 3 | W23: =(B23*C23)*V23 -> 892500 | X23: 3 | Y23: =(B23*C23)*X23 -> 892500 | Z23: 3 | AA23: =(B23*C23)*Z23 -> 892500
A24: Design Project Shop | B24: 500 | C24: 850 | D24: 0 | E24: =(B24*C24)*D24 -> 0 | F24: 0 | G24: =(B24*C24)*F24 -> 0 | H24: 0 | I24: =(B24*C24)*H24 -> 0 | J24: 0 | K24: =(B24*C24)*J24 -> 0 | L24: 0 | M24: =(B24*C24)*L24 -> 0 | N24: 0 | O24: =(B24*C24)*N24 -> 0 | P24: 1 | Q24: =(B24*C24)*P24 -> 425000 | R24: 1 | S24: =(B24*C24)*R24 -> 425000 | T24: 1 | U24: =(B24*C24)*T24 -> 425000 | V24: 1 | W24: =(B24*C24)*V24 -> 425000 | X24: 1 | Y24: =(B24*C24)*X24 -> 425000 | Z24: 1 | AA24: =(B24*C24)*Z24 -> 425000
K25: =(B25*C25)*J25 -> 0 | M25: =(B25*C25)*L25 -> 0 | O25: =(B25*C25)*N25 -> 0 | Q25: =(B25*C25)*P25 -> 0 | S25: =(B25*C25)*R25 -> 0 | U25: =(B25*C25)*T25 -> 0 | W25: =(B25*C25)*V25 -> 0 | Y25: =(B25*C25)*X25 -> 0 | AA25: =(B25*C25)*Z25 -> 0
A26: Design Project office | B26: 100 | C26: 850 | D26: 0 | E26: =(B26*C26)*D26 -> 0 | F26: 0 | G26: =(B26*C26)*F26 -> 0 | H26: 0 | I26: =(B26*C26)*H26 -> 0 | J26: 0 | K26: =(B26*C26)*J26 -> 0 | L26: 0 | M26: =(B26*C26)*L26 -> 0 | N26: 0 | O26: =(B26*C26)*N26 -> 0 | P26: 5 | Q26: =(B26*C26)*P26 -> 425000 | R26: 5 | S26: =(B26*C26)*R26 -> 425000 | T26: 5 | U26: =(B26*C26)*T26 -> 425000 | V26: 5 | W26: =(B26*C26)*V26 -> 425000 | X26: 5 | Y26: =(B26*C26)*X26 -> 425000 | Z26: 5 | AA26: =(B26*C26)*Z26 -> 425000
A27: Design Project office | B27: 150 | C27: 850 | D27: 0 | E27: =(B27*C27)*D27 -> 0 | F27: 0 | G27: =(B27*C27)*F27 -> 0 | H27: 0 | I27: =(B27*C27)*H27 -> 0 | J27: 0 | K27: =(B27*C27)*J27 -> 0 | L27: 0 | M27: =(B27*C27)*L27 -> 0 | N27: 0 | O27: =(B27*C27)*N27 -> 0 | P27: 4 | Q27: =(B27*C27)*P27 -> 510000 | R27: 4 | S27: =(B27*C27)*R27 -> 510000 | T27: 4 | U27: =(B27*C27)*T27 -> 510000 | V27: 4 | W27: =(B27*C27)*V27 -> 510000 | X27: 4 | Y27: =(B27*C27)*X27 -> 510000 | Z27: 4 | AA27: =(B27*C27)*Z27 -> 510000
A28: Design Project office | B28: 250 | C28: 850 | D28: 0 | E28: =(B28*C28)*D28 -> 0 | F28: 0 | G28: =(B28*C28)*F28 -> 0 | H28: 0 | I28: =(B28*C28)*H28 -> 0 | J28: 0 | K28: =(B28*C28)*J28 -> 0 | L28: 0 | M28: =(B28*C28)*L28 -> 0 | N28: 0 | O28: =(B28*C28)*N28 -> 0 | P28: 3 | Q28: =(B28*C28)*P28 -> 637500 | R28: 3 | S28: =(B28*C28)*R28 -> 637500 | T28: 3 | U28: =(B28*C28)*T28 -> 637500 | V28: 3 | W28: =(B28*C28)*V28 -> 637500 | X28: 3 | Y28: =(B28*C28)*X28 -> 637500 | Z28: 3 | AA28: =(B28*C28)*Z28 -> 637500
A29: Design Project office | B29: 350 | C29: 850 | D29: 0 | E29: =(B29*C29)*D29 -> 0 | F29: 0 | G29: =(B29*C29)*F29 -> 0 | H29: 0 | I29: =(B29*C29)*H29 -> 0 | J29: 0 | K29: =(B29*C29)*J29 -> 0 | L29: 0 | M29: =(B29*C29)*L29 -> 0 | N29: 0 | O29: =(B29*C29)*N29 -> 0 | P29: 3 | Q29: =(B29*C29)*P29 -> 892500 | R29: 3 | S29: =(B29*C29)*R29 -> 892500 | T29: 3 | U29: =(B29*C29)*T29 -> 892500 | V29: 3 | W29: =(B29*C29)*V29 -> 892500 | X29: 3 | Y29: =(B29*C29)*X29 -> 892500 | Z29: 3 | AA29: =(B29*C29)*Z29 -> 892500
A30: Design Project office | B30: 500 | C30: 850 | D30: 0 | E30: =(B30*C30)*D30 -> 0 | F30: 0 | G30: =(B30*C30)*F30 -> 0 | H30: 0 | I30: =(B30*C30)*H30 -> 0 | J30: 0 | K30: =(B30*C30)*J30 -> 0 | L30: 0 | M30: =(B30*C30)*L30 -> 0 | N30: 0 | O30: =(B30*C30)*N30 -> 0 | P30: 1 | Q30: =(B30*C30)*P30 -> 425000 | R30: 1 | S30: =(B30*C30)*R30 -> 425000 | T30: 1 | U30: =(B30*C30)*T30 -> 425000 | V30: 1 | W30: =(B30*C30)*V30 -> 425000 | X30: 1 | Y30: =(B30*C30)*X30 -> 425000 | Z30: 1 | AA30: =(B30*C30)*Z30 -> 425000
D32: 0.1 | E32: =SUM(E10:E30) -> 0 | F32: 0.1 | G32: =SUM(G10:G30) -> 0 | H32: 0.1 | I32: =SUM(I10:I30) -> 0 | J32: 0.1 | K32: =SUM(K10:K30) -> 0 | L32: 0.1 | M32: =SUM(M10:M30) -> 0 | N32: 0.1 | O32: =SUM(O10:O30) -> 0 | P32: 0.1 | Q32: =SUM(Q10:Q30) -> 9182550 | R32: 0.1 | S32: =SUM(S10:S30) -> 9182550 | T32: 0.1 | U32: =SUM(U10:U30) -> 9182550 | V32: 0.1 | W32: =SUM(W10:W31) -> 9182550 | X32: 0.1 | Y32: =SUM(Y10:Y31) -> 9182550 | Z32: 0.1 | AA32: =SUM(AA10:AA31) -> 9182550
E33: =E32*D32 -> 0 | G33: =G32*F32 -> 0 | I33: =I32*H32 -> 0 | K33: =K32*J32 -> 0 | M33: =M32*L32 -> 0 | O33: =O32*N32 -> 0 | Q33: =Q32*P32 -> 918255 | S33: =S32*R32 -> 918255 | U33: =U32*T32 -> 918255 | W33: =W32*V32 -> 918255 | Y33: =Y32*X32 -> 918255 | AA33: =AA32*Z32 -> 918255 | AB33: =SUM(AA33,Y33,W33,U33,S33,Q33,O33,M33,K33,I33,G33,E33) -> 5509530
K34: =(B34*C34)*J34 -> 0 | M34: =(B34*C34)*L34 -> 0 | O34: =(B34*C34)*N34 -> 0 | Q34: =(B34*C34)*P34 -> 0 | S34: =(B34*C34)*R34 -> 0 | U34: =(B34*C34)*T34 -> 0 | W34: =(B34*C34)*V34 -> 0 | Y34: =(B34*C34)*X34 -> 0 | AA34: =(B34*C34)*Z34 -> 0
A35: contractor Project condo | B35: 26 | C35: 15000 | D35: 0 | E35: =(B35*C35)*D35 -> 0 | F35: 0 | G35: =(B35*C35)*F35 -> 0 | H35: 0 | I35: =(B35*C35)*H35 -> 0 | J35: 0 | K35: =(B35*C35)*J35 -> 0 | L35: 0 | M35: =(B35*C35)*L35 -> 0 | N35: 0 | O35: =(B35*C35)*N35 -> 0 | P35: 10 | Q35: =(B35*C35)*P35 -> 3900000 | R35: 10 | S35: =(B35*C35)*R35 -> 3900000 | T35: 10 | U35: =(B35*C35)*T35 -> 3900000 | V35: 10 | W35: =(B35*C35)*V35 -> 3900000 | X35: 10 | Y35: =(B35*C35)*X35 -> 3900000 | Z35: 10 | AA35: =(B35*C35)*Z35 -> 3900000
A36: contractor Project condo | B36: 33 | C36: 15000 | D36: 0 | E36: =(B36*C36)*D36 -> 0 | F36: 0 | G36: =(B36*C36)*F36 -> 0 | H36: 0 | I36: =(B36*C36)*H36 -> 0 | J36: 0 | K36: =(B36*C36)*J36 -> 0 | L36: 0 | M36: =(B36*C36)*L36 -> 0 | N36: 0 | O36: =(B36*C36)*N36 -> 0 | P36: 5 | Q36: =(B36*C36)*P36 -> 2475000 | R36: 5 | S36: =(B36*C36)*R36 -> 2475000 | T36: 5 | U36: =(B36*C36)*T36 -> 2475000 | V36: 5 | W36: =(B36*C36)*V36 -> 2475000 | X36: 5 | Y36: =(B36*C36)*X36 -> 2475000 | Z36: 5 | AA36: =(B36*C36)*Z36 -> 2475000
A37: contractor Project condo | B37: 64 | C37: 15000 | D37: 0 | E37: =(B37*C37)*D37 -> 0 | F37: 0 | G37: =(B37*C37)*F37 -> 0 | H37: 0 | I37: =(B37*C37)*H37 -> 0 | J37: 0 | K37: =(B37*C37)*J37 -> 0 | L37: 0 | M37: =(B37*C37)*L37 -> 0 | N37: 0 | O37: =(B37*C37)*N37 -> 0 | P37: 2 | Q37: =(B37*C37)*P37 -> 1920000 | R37: 2 | S37: =(B37*C37)*R37 -> 1920000 | T37: 2 | U37: =(B37*C37)*T37 -> 1920000 | V37: 2 | W37: =(B37*C37)*V37 -> 1920000 | X37: 2 | Y37: =(B37*C37)*X37 -> 1920000 | Z37: 2 | AA37: =(B37*C37)*Z37 -> 1920000
A38: contractor Project condo | B38: 100 | C38: 15000 | D38: 0 | E38: =(B38*C38)*D38 -> 0 | F38: 0 | G38: =(B38*C38)*F38 -> 0 | H38: 0 | I38: =(B38*C38)*H38 -> 0 | J38: 0 | K38: =(B38*C38)*J38 -> 0 | L38: 0 | M38: =(B38*C38)*L38 -> 0 | N38: 0 | O38: =(B38*C38)*N38 -> 0 | P38: 0 | Q38: =(B38*C38)*P38 -> 0 | R38: 0 | S38: =(B38*C38)*R38 -> 0 | T38: 0 | U38: =(B38*C38)*T38 -> 0 | V38: 0 | W38: =(B38*C38)*V38 -> 0 | X38: 0 | Y38: =(B38*C38)*X38 -> 0 | Z38: 0 | AA38: =(B38*C38)*Z38 -> 0
K39: =(B39*C39)*J39 -> 0 | M39: =(B39*C39)*L39 -> 0 | O39: =(B39*C39)*N39 -> 0 | Q39: =(B39*C39)*P39 -> 0 | S39: =(B39*C39)*R39 -> 0 | U39: =(B39*C39)*T39 -> 0 | W39: =(B39*C39)*V39 -> 0 | Y39: =(B39*C39)*X39 -> 0 | AA39: =(B39*C39)*Z39 -> 0
A40: contractor Project House | B40: 150 | C40: 15000 | D40: 0 | E40: =(B40*C40)*D40 -> 0 | F40: 0 | G40: =(B40*C40)*F40 -> 0 | H40: 0 | I40: =(B40*C40)*H40 -> 0 | J40: 0 | K40: =(B40*C40)*J40 -> 0 | L40: 0 | M40: =(B40*C40)*L40 -> 0 | N40: 0 | O40: =(B40*C40)*N40 -> 0 | P40: 10 | Q40: =(B40*C40)*P40 -> 22500000 | R40: 10 | S40: =(B40*C40)*R40 -> 22500000 | T40: 10 | U40: =(B40*C40)*T40 -> 22500000 | V40: 10 | W40: =(B40*C40)*V40 -> 22500000 | X40: 10 | Y40: =(B40*C40)*X40 -> 22500000 | Z40: 10 | AA40: =(B40*C40)*Z40 -> 22500000
A41: contractor Project House | B41: 250 | C41: 15000 | D41: 0 | E41: =(B41*C41)*D41 -> 0 | F41: 0 | G41: =(B41*C41)*F41 -> 0 | H41: 0 | I41: =(B41*C41)*H41 -> 0 | J41: 0 | K41: =(B41*C41)*J41 -> 0 | L41: 0 | M41: =(B41*C41)*L41 -> 0 | N41: 0 | O41: =(B41*C41)*N41 -> 0 | P41: 5 | Q41: =(B41*C41)*P41 -> 18750000 | R41: 5 | S41: =(B41*C41)*R41 -> 18750000 | T41: 5 | U41: =(B41*C41)*T41 -> 18750000 | V41: 5 | W41: =(B41*C41)*V41 -> 18750000 | X41: 5 | Y41: =(B41*C41)*X41 -> 18750000 | Z41: 5 | AA41: =(B41*C41)*Z41 -> 18750000
A42: contractor Project House | B42: 350 | C42: 15000 | D42: 0 | E42: =(B42*C42)*D42 -> 0 | F42: 0 | G42: =(B42*C42)*F42 -> 0 | H42: 0 | I42: =(B42*C42)*H42 -> 0 | J42: 0 | K42: =(B42*C42)*J42 -> 0 | L42: 0 | M42: =(B42*C42)*L42 -> 0 | N42: 0 | O42: =(B42*C42)*N42 -> 0 | P42: 2 | Q42: =(B42*C42)*P42 -> 10500000 | R42: 2 | S42: =(B42*C42)*R42 -> 10500000 | T42: 2 | U42: =(B42*C42)*T42 -> 10500000 | V42: 2 | W42: =(B42*C42)*V42 -> 10500000 | X42: 2 | Y42: =(B42*C42)*X42 -> 10500000 | Z42: 2 | AA42: =(B42*C42)*Z42 -> 10500000
A43: contractor Project House | B43: 500 | C43: 15000 | D43: 0 | E43: =(B43*C43)*D43 -> 0 | F43: 0 | G43: =(B43*C43)*F43 -> 0 | H43: 0 | I43: =(B43*C43)*H43 -> 0 | J43: 0 | K43: =(B43*C43)*J43 -> 0 | L43: 0 | M43: =(B43*C43)*L43 -> 0 | N43: 0 | O43: =(B43*C43)*N43 -> 0 | P43: 0 | Q43: =(B43*C43)*P43 -> 0 | R43: 0 | S43: =(B43*C43)*R43 -> 0 | T43: 0 | U43: =(B43*C43)*T43 -> 0 | V43: 0 | W43: =(B43*C43)*V43 -> 0 | X43: 0 | Y43: =(B43*C43)*X43 -> 0 | Z43: 0 | AA43: =(B43*C43)*Z43 -> 0
K44: =(B44*C44)*J44 -> 0 | M44: =(B44*C44)*L44 -> 0 | O44: =(B44*C44)*N44 -> 0 | Q44: =(B44*C44)*P44 -> 0 | S44: =(B44*C44)*R44 -> 0 | U44: =(B44*C44)*T44 -> 0 | W44: =(B44*C44)*V44 -> 0 | Y44: =(B44*C44)*X44 -> 0 | AA44: =(B44*C44)*Z44 -> 0
A45: contractor Project Shop | B45: 100 | C45: 20000 | D45: 0 | E45: =(B45*C45)*D45 -> 0 | F45: 0 | G45: =(B45*C45)*F45 -> 0 | H45: 0 | I45: =(B45*C45)*H45 -> 0 | J45: 0 | K45: =(B45*C45)*J45 -> 0 | L45: 0 | M45: =(B45*C45)*L45 -> 0 | N45: 0 | O45: =(B45*C45)*N45 -> 0 | P45: 5 | Q45: =(B45*C45)*P45 -> 10000000 | R45: 5 | S45: =(B45*C45)*R45 -> 10000000 | T45: 5 | U45: =(B45*C45)*T45 -> 10000000 | V45: 5 | W45: =(B45*C45)*V45 -> 10000000 | X45: 5 | Y45: =(B45*C45)*X45 -> 10000000 | Z45: 5 | AA45: =(B45*C45)*Z45 -> 10000000
A46: contractor Project Shop | B46: 150 | C46: 20000 | D46: 0 | E46: =(B46*C46)*D46 -> 0 | F46: 0 | G46: =(B46*C46)*F46 -> 0 | H46: 0 | I46: =(B46*C46)*H46 -> 0 | J46: 0 | K46: =(B46*C46)*J46 -> 0 | L46: 0 | M46: =(B46*C46)*L46 -> 0 | N46: 0 | O46: =(B46*C46)*N46 -> 0 | P46: 4 | Q46: =(B46*C46)*P46 -> 12000000 | R46: 4 | S46: =(B46*C46)*R46 -> 12000000 | T46: 4 | U46: =(B46*C46)*T46 -> 12000000 | V46: 4 | W46: =(B46*C46)*V46 -> 12000000 | X46: 4 | Y46: =(B46*C46)*X46 -> 12000000 | Z46: 4 | AA46: =(B46*C46)*Z46 -> 12000000
A47: contractor Project Shop | B47: 250 | C47: 20000 | D47: 0 | E47: =(B47*C47)*D47 -> 0 | F47: 0 | G47: =(B47*C47)*F47 -> 0 | H47: 0 | I47: =(B47*C47)*H47 -> 0 | J47: 0 | K47: =(B47*C47)*J47 -> 0 | L47: 0 | M47: =(B47*C47)*L47 -> 0 | N47: 0 | O47: =(B47*C47)*N47 -> 0 | P47: 3 | Q47: =(B47*C47)*P47 -> 15000000 | R47: 3 | S47: =(B47*C47)*R47 -> 15000000 | T47: 3 | U47: =(B47*C47)*T47 -> 15000000 | V47: 3 | W47: =(B47*C47)*V47 -> 15000000 | X47: 3 | Y47: =(B47*C47)*X47 -> 15000000 | Z47: 3 | AA47: =(B47*C47)*Z47 -> 15000000
A48: contractor Project Shop | B48: 350 | C48: 20000 | D48: 0 | E48: =(B48*C48)*D48 -> 0 | F48: 0 | G48: =(B48*C48)*F48 -> 0 | H48: 0 | I48: =(B48*C48)*H48 -> 0 | J48: 0 | K48: =(B48*C48)*J48 -> 0 | L48: 0 | M48: =(B48*C48)*L48 -> 0 | N48: 0 | O48: =(B48*C48)*N48 -> 0 | P48: 3 | Q48: =(B48*C48)*P48 -> 21000000 | R48: 3 | S48: =(B48*C48)*R48 -> 21000000 | T48: 3 | U48: =(B48*C48)*T48 -> 21000000 | V48: 3 | W48: =(B48*C48)*V48 -> 21000000 | X48: 3 | Y48: =(B48*C48)*X48 -> 21000000 | Z48: 3 | AA48: =(B48*C48)*Z48 -> 21000000
A49: contractor Project Shop | B49: 500 | C49: 20000 | D49: 0 | E49: =(B49*C49)*D49 -> 0 | F49: 0 | G49: =(B49*C49)*F49 -> 0 | H49: 0 | I49: =(B49*C49)*H49 -> 0 | J49: 0 | K49: =(B49*C49)*J49 -> 0 | L49: 0 | M49: =(B49*C49)*L49 -> 0 | N49: 0 | O49: =(B49*C49)*N49 -> 0 | P49: 1 | Q49: =(B49*C49)*P49 -> 10000000 | R49: 1 | S49: =(B49*C49)*R49 -> 10000000 | T49: 1 | U49: =(B49*C49)*T49 -> 10000000 | V49: 1 | W49: =(B49*C49)*V49 -> 10000000 | X49: 1 | Y49: =(B49*C49)*X49 -> 10000000 | Z49: 1 | AA49: =(B49*C49)*Z49 -> 10000000
K50: =(B50*C50)*J50 -> 0 | M50: =(B50*C50)*L50 -> 0 | O50: =(B50*C50)*N50 -> 0 | Q50: =(B50*C50)*P50 -> 0 | S50: =(B50*C50)*R50 -> 0 | U50: =(B50*C50)*T50 -> 0 | W50: =(B50*C50)*V50 -> 0 | Y50: =(B50*C50)*X50 -> 0 | AA50: =(B50*C50)*Z50 -> 0
A51: contractor Project office | B51: 100 | C51: 10000 | D51: 0 | E51: =(B51*C51)*D51 -> 0 | F51: 0 | G51: =(B51*C51)*F51 -> 0 | H51: 0 | I51: =(B51*C51)*H51 -> 0 | J51: 0 | K51: =(B51*C51)*J51 -> 0 | L51: 0 | M51: =(B51*C51)*L51 -> 0 | N51: 0 | O51: =(B51*C51)*N51 -> 0 | P51: 5 | Q51: =(B51*C51)*P51 -> 5000000 | R51: 5 | S51: =(B51*C51)*R51 -> 5000000 | T51: 5 | U51: =(B51*C51)*T51 -> 5000000 | V51: 5 | W51: =(B51*C51)*V51 -> 5000000 | X51: 5 | Y51: =(B51*C51)*X51 -> 5000000 | Z51: 5 | AA51: =(B51*C51)*Z51 -> 5000000
A52: contractor Project office | B52: 150 | C52: 10000 | D52: 0 | E52: =(B52*C52)*D52 -> 0 | F52: 0 | G52: =(B52*C52)*F52 -> 0 | H52: 0 | I52: =(B52*C52)*H52 -> 0 | J52: 0 | K52: =(B52*C52)*J52 -> 0 | L52: 0 | M52: =(B52*C52)*L52 -> 0 | N52: 0 | O52: =(B52*C52)*N52 -> 0 | P52: 4 | Q52: =(B52*C52)*P52 -> 6000000 | R52: 4 | S52: =(B52*C52)*R52 -> 6000000 | T52: 4 | U52: =(B52*C52)*T52 -> 6000000 | V52: 4 | W52: =(B52*C52)*V52 -> 6000000 | X52: 4 | Y52: =(B52*C52)*X52 -> 6000000 | Z52: 4 | AA52: =(B52*C52)*Z52 -> 6000000
A53: contractor Project office | B53: 250 | C53: 10000 | D53: 0 | E53: =(B53*C53)*D53 -> 0 | F53: 0 | G53: =(B53*C53)*F53 -> 0 | H53: 0 | I53: =(B53*C53)*H53 -> 0 | J53: 0 | K53: =(B53*C53)*J53 -> 0 | L53: 0 | M53: =(B53*C53)*L53 -> 0 | N53: 0 | O53: =(B53*C53)*N53 -> 0 | P53: 3 | Q53: =(B53*C53)*P53 -> 7500000 | R53: 3 | S53: =(B53*C53)*R53 -> 7500000 | T53: 3 | U53: =(B53*C53)*T53 -> 7500000 | V53: 3 | W53: =(B53*C53)*V53 -> 7500000 | X53: 3 | Y53: =(B53*C53)*X53 -> 7500000 | Z53: 3 | AA53: =(B53*C53)*Z53 -> 7500000
A54: contractor Project office | B54: 350 | C54: 10000 | D54: 0 | E54: =(B54*C54)*D54 -> 0 | F54: 0 | G54: =(B54*C54)*F54 -> 0 | H54: 0 | I54: =(B54*C54)*H54 -> 0 | J54: 0 | K54: =(B54*C54)*J54 -> 0 | L54: 0 | M54: =(B54*C54)*L54 -> 0 | N54: 0 | O54: =(B54*C54)*N54 -> 0 | P54: 3 | Q54: =(B54*C54)*P54 -> 10500000 | R54: 3 | S54: =(B54*C54)*R54 -> 10500000 | T54: 3 | U54: =(B54*C54)*T54 -> 10500000 | V54: 3 | W54: =(B54*C54)*V54 -> 10500000 | X54: 3 | Y54: =(B54*C54)*X54 -> 10500000 | Z54: 3 | AA54: =(B54*C54)*Z54 -> 10500000
A55: contractor Project office | B55: 500 | C55: 10000 | D55: 0 | E55: =(B55*C55)*D55 -> 0 | F55: 0 | G55: =(B55*C55)*F55 -> 0 | H55: 0 | I55: =(B55*C55)*H55 -> 0 | J55: 0 | K55: =(B55*C55)*J55 -> 0 | L55: 0 | M55: =(B55*C55)*L55 -> 0 | N55: 0 | O55: =(B55*C55)*N55 -> 0 | P55: 1 | Q55: =(B55*C55)*P55 -> 5000000 | R55: 1 | S55: =(B55*C55)*R55 -> 5000000 | T55: 1 | U55: =(B55*C55)*T55 -> 5000000 | V55: 1 | W55: =(B55*C55)*V55 -> 5000000 | X55: 1 | Y55: =(B55*C55)*X55 -> 5000000 | Z55: 1 | AA55: =(B55*C55)*Z55 -> 5000000
D57: 0.05 | E57: =SUM(E35:E55) -> 0 | F57: 0.05 | G57: =SUM(G35:G55) -> 0 | H57: 0.05 | I57: =SUM(I35:I55) -> 0 | J57: 0.05 | K57: =SUM(K35:K55) -> 0 | L57: 0.05 | M57: =SUM(M35:M55) -> 0 | N57: 0.05 | O57: =SUM(O35:O55) -> 0 | P57: 0.05 | Q57: =SUM(Q35:Q55) -> 162045000 | R57: 0.05 | S57: =SUM(S35:S55) -> 162045000 | T57: 0.05 | U57: =SUM(U35:U55) -> 162045000 | V57: 0.05 | W57: =SUM(W35:W55) -> 162045000 | X57: 0.05 | Y57: =SUM(Y35:Y55) -> 162045000 | Z57: 0.05 | AA57: =SUM(AA35:AA55) -> 162045000
E58: =E57*D57 -> 0 | G58: =G57*F57 -> 0 | I58: =I57*H57 -> 0 | K58: =K57*J57 -> 0 | M58: =M57*L57 -> 0 | O58: =O57*N57 -> 0 | Q58: =Q57*P57 -> 8102250 | S58: =S57*R57 -> 8102250 | U58: =U57*T57 -> 8102250 | W58: =W57*V57 -> 8102250 | Y58: =Y57*X57 -> 8102250 | AA58: =AA57*Z57 -> 8102250 | AB58: =SUM(AA58,Y58,W58,U58,S58,Q58,O58,M58,K58,I58,G58,E58) -> 48613500
A60: Electrician Project condo | B60: 26 | C60: 3500 | D60: 0 | E60: =D60*C60 -> 0 | F60: 0 | G60: =F60*C60 -> 0 | H60: 0 | I60: =H60*C60 -> 0 | J60: 0 | K60: =J60*C60 -> 0 | L60: 0 | M60: =L60*C60 -> 0 | N60: 0 | O60: =N60*C60 -> 0 | P60: 10 | Q60: =P60*C60 -> 35000 | R60: 10 | S60: =R60*C60 -> 35000 | T60: 10 | U60: =T60*C60 -> 35000 | V60: 10 | W60: =V60*C60 -> 35000 | X60: 10 | Y60: =X60*C60 -> 35000 | Z60: 10 | AA60: =Z60*C60 -> 35000
A61: Electrician Project condo | B61: 33 | C61: 4500 | D61: 0 | E61: =D61*C61 -> 0 | F61: 0 | G61: =F61*C61 -> 0 | H61: 0 | I61: =H61*C61 -> 0 | J61: 0 | K61: =J61*C61 -> 0 | L61: 0 | M61: =L61*C61 -> 0 | N61: 0 | O61: =N61*C61 -> 0 | P61: 5 | Q61: =P61*C61 -> 22500 | R61: 5 | S61: =R61*C61 -> 22500 | T61: 5 | U61: =T61*C61 -> 22500 | V61: 5 | W61: =V61*C61 -> 22500 | X61: 5 | Y61: =X61*C61 -> 22500 | Z61: 5 | AA61: =Z61*C61 -> 22500
A62: Electrician Project condo | B62: 64 | C62: 5500 | D62: 0 | E62: =D62*C62 -> 0 | F62: 0 | G62: =F62*C62 -> 0 | H62: 0 | I62: =H62*C62 -> 0 | J62: 0 | K62: =J62*C62 -> 0 | L62: 0 | M62: =L62*C62 -> 0 | N62: 0 | O62: =N62*C62 -> 0 | P62: 2 | Q62: =P62*C62 -> 11000 | R62: 2 | S62: =R62*C62 -> 11000 | T62: 2 | U62: =T62*C62 -> 11000 | V62: 2 | W62: =V62*C62 -> 11000 | X62: 2 | Y62: =X62*C62 -> 11000 | Z62: 2 | AA62: =Z62*C62 -> 11000
A63: Electrician Project condo | B63: 100 | C63: 6500 | D63: 0 | E63: =D63*C63 -> 0 | F63: 0 | G63: =F63*C63 -> 0 | H63: 0 | I63: =H63*C63 -> 0 | J63: 0 | K63: =J63*C63 -> 0 | L63: 0 | M63: =L63*C63 -> 0 | N63: 0 | O63: =N63*C63 -> 0 | P63: 0 | Q63: =P63*C63 -> 0 | R63: 0 | S63: =R63*C63 -> 0 | T63: 0 | U63: =T63*C63 -> 0 | V63: 0 | W63: =V63*C63 -> 0 | X63: 0 | Y63: =X63*C63 -> 0 | Z63: 0 | AA63: =Z63*C63 -> 0
A65: Electrician Project House | B65: 150 | C65: 10000 | D65: 0 | E65: =D65*C65 -> 0 | F65: 0 | G65: =F65*C65 -> 0 | H65: 0 | I65: =H65*C65 -> 0 | J65: 0 | K65: =J65*C65 -> 0 | L65: 0 | M65: =L65*C65 -> 0 | N65: 0 | O65: =N65*C65 -> 0 | P65: 10 | Q65: =P65*C65 -> 100000 | R65: 10 | S65: =R65*C65 -> 100000 | T65: 10 | U65: =T65*C65 -> 100000 | V65: 10 | W65: =V65*C65 -> 100000 | X65: 10 | Y65: =X65*C65 -> 100000 | Z65: 10 | AA65: =Z65*C65 -> 100000
A66: Electrician Project House | B66: 250 | C66: 18000 | D66: 0 | E66: =D66*C66 -> 0 | F66: 0 | G66: =F66*C66 -> 0 | H66: 0 | I66: =H66*C66 -> 0 | J66: 0 | K66: =J66*C66 -> 0 | L66: 0 | M66: =L66*C66 -> 0 | N66: 0 | O66: =N66*C66 -> 0 | P66: 5 | Q66: =P66*C66 -> 90000 | R66: 5 | S66: =R66*C66 -> 90000 | T66: 5 | U66: =T66*C66 -> 90000 | V66: 5 | W66: =V66*C66 -> 90000 | X66: 5 | Y66: =X66*C66 -> 90000 | Z66: 5 | AA66: =Z66*C66 -> 90000
A67: Electrician Project House | B67: 350 | C67: 25000 | D67: 0 | E67: =D67*C67 -> 0 | F67: 0 | G67: =F67*C67 -> 0 | H67: 0 | I67: =H67*C67 -> 0 | J67: 0 | K67: =J67*C67 -> 0 | L67: 0 | M67: =L67*C67 -> 0 | N67: 0 | O67: =N67*C67 -> 0 | P67: 2 | Q67: =P67*C67 -> 50000 | R67: 2 | S67: =R67*C67 -> 50000 | T67: 2 | U67: =T67*C67 -> 50000 | V67: 2 | W67: =V67*C67 -> 50000 | X67: 2 | Y67: =X67*C67 -> 50000 | Z67: 2 | AA67: =Z67*C67 -> 50000
A68: Electrician Project House | B68: 500 | C68: 40000 | D68: 0 | E68: =D68*C68 -> 0 | F68: 0 | G68: =F68*C68 -> 0 | H68: 0 | I68: =H68*C68 -> 0 | J68: 0 | K68: =J68*C68 -> 0 | L68: 0 | M68: =L68*C68 -> 0 | N68: 0 | O68: =N68*C68 -> 0 | P68: 0 | Q68: =P68*C68 -> 0 | R68: 0 | S68: =R68*C68 -> 0 | T68: 0 | U68: =T68*C68 -> 0 | V68: 0 | W68: =V68*C68 -> 0 | X68: 0 | Y68: =X68*C68 -> 0 | Z68: 0 | AA68: =Z68*C68 -> 0
A70: Electrician Project Shop | B70: 100 | C70: 8000 | D70: 0 | E70: =D70*C70 -> 0 | F70: 0 | G70: =F70*C70 -> 0 | H70: 0 | I70: =H70*C70 -> 0 | J70: 0 | K70: =J70*C70 -> 0 | L70: 0 | M70: =L70*C70 -> 0 | N70: 0 | O70: =N70*C70 -> 0 | P70: 5 | Q70: =P70*C70 -> 40000 | R70: 5 | S70: =R70*C70 -> 40000 | T70: 5 | U70: =T70*C70 -> 40000 | V70: 5 | W70: =V70*C70 -> 40000 | X70: 5 | Y70: =X70*C70 -> 40000 | Z70: 5 | AA70: =Z70*C70 -> 40000
A71: Electrician Project Shop | B71: 150 | C71: 12000 | D71: 0 | E71: =D71*C71 -> 0 | F71: 0 | G71: =F71*C71 -> 0 | H71: 0 | I71: =H71*C71 -> 0 | J71: 0 | K71: =J71*C71 -> 0 | L71: 0 | M71: =L71*C71 -> 0 | N71: 0 | O71: =N71*C71 -> 0 | P71: 4 | Q71: =P71*C71 -> 48000 | R71: 4 | S71: =R71*C71 -> 48000 | T71: 4 | U71: =T71*C71 -> 48000 | V71: 4 | W71: =V71*C71 -> 48000 | X71: 4 | Y71: =X71*C71 -> 48000 | Z71: 4 | AA71: =Z71*C71 -> 48000
A72: Electrician Project Shop | B72: 250 | C72: 20000 | D72: 0 | E72: =D72*C72 -> 0 | F72: 0 | G72: =F72*C72 -> 0 | H72: 0 | I72: =H72*C72 -> 0 | J72: 0 | K72: =J72*C72 -> 0 | L72: 0 | M72: =L72*C72 -> 0 | N72: 0 | O72: =N72*C72 -> 0 | P72: 3 | Q72: =P72*C72 -> 60000 | R72: 3 | S72: =R72*C72 -> 60000 | T72: 3 | U72: =T72*C72 -> 60000 | V72: 3 | W72: =V72*C72 -> 60000 | X72: 3 | Y72: =X72*C72 -> 60000 | Z72: 3 | AA72: =Z72*C72 -> 60000
A73: Electrician Project Shop | B73: 350 | C73: 28000 | D73: 0 | E73: =D73*C73 -> 0 | F73: 0 | G73: =F73*C73 -> 0 | H73: 0 | I73: =H73*C73 -> 0 | J73: 0 | K73: =J73*C73 -> 0 | L73: 0 | M73: =L73*C73 -> 0 | N73: 0 | O73: =N73*C73 -> 0 | P73: 3 | Q73: =P73*C73 -> 84000 | R73: 3 | S73: =R73*C73 -> 84000 | T73: 3 | U73: =T73*C73 -> 84000 | V73: 3 | W73: =V73*C73 -> 84000 | X73: 3 | Y73: =X73*C73 -> 84000 | Z73: 3 | AA73: =Z73*C73 -> 84000
... A79: Electrician Project office | B79: 350 | C79: 28000 | D79: 0 | E79: =D79*C79 -> 0 | F79: 0 | G79: =F79*C79 -> 0 | H79: 0 | I79: =H79*C79 -> 0 | J79: 0 | K79: =J79*C79 -> 0 | L79: 0 | M79: =L79*C79 -> 0 | N79: 0 | O79: =N79*C79 -> 0 | P79: 3 | Q79: =P79*C79 -> 84000 | R79: 3 | S79: =R79*C79 -> 84000 | T79: 3 | U79: =T79*C79 -> 84000 | V79: 3 | W79: =V79*C79 -> 84000 | X79: 3 | Y79: =X79*C79 -> 84000 | Z79: 3 | AA79: =Z79*C79 -> 84000
A80: Electrician Project office | B80: 500 | C80: 50000 | D80: 0 | E80: =D80*C80 -> 0 | F80: 0 | G80: =F80*C80 -> 0 | H80: 0 | I80: =H80*C80 -> 0 | J80: 0 | K80: =J80*C80 -> 0 | L80: 0 | M80: =C80*L80 -> 0 | N80: 0 | O80: =N80*C80 -> 0 | P80: 1 | Q80: =P80*C80 -> 50000 | R80: 1 | S80: =R80*C80 -> 50000 | T80: 1 | U80: =T80*C80 -> 50000 | V80: 1 | W80: =V80*C80 -> 50000 | X80: 1 | Y80: =X80*C80 -> 50000 | Z80: 1 | AA80: =Z80*C80 -> 50000
D82: 0.1 | E82: =SUM(E60:E80) -> 0 | F82: 0.1 | G82: =SUM(G60:G80) -> 0 | H82: 0.1 | I82: =SUM(I60:I80) -> 0 | J82: 0.1 | K82: =SUM(K60:K80) -> 0 | L82: 0.1 | M82: =SUM(M60:M80) -> 0 | N82: 0.1 | O82: =SUM(O60:O80) -> 0 | P82: 0.05 | Q82: =SUM(Q60:Q80) -> 872500 | R82: 0.05 | S82: =SUM(S60:S80) -> 872500 | T82: 0.05 | U82: =SUM(U60:U80) -> 872500 | V82: 0.05 | W82: =SUM(W60:W80) -> 872500 | X82: 0.05 | Y82: =SUM(Y60:Y80) -> 872500 | Z82: 0.05 | AA82: =SUM(AA60:AA80) -> 872500
E83: =E82*D82 -> 0 | G83: =G82*F82 -> 0 | I83: =I82*H82 -> 0 | K83: =K82*J82 -> 0 | M83: =M82*L82 -> 0 | O83: =O82*N82 -> 0 | Q83: =Q82*P82 -> 43625 | S83: =S82*R82 -> 43625 | U83: =U82*T82 -> 43625 | W83: =W82*V82 -> 43625 | Y83: =Y82*X82 -> 43625 | AA83: =AA82*Z82 -> 43625 | AB83: =SUM(AA83,Y83,W83,U83,S83,Q83,O83,M83,K83,I83,G83,E83) -> 261750
A85: Certain Project condo | B85: 26 | C85: 18000 | D85: 0 | E85: =D85*C85 -> 0 | F85: 0 | G85: =F85*C85 -> 0 | H85: 0 | I85: =H85*C85 -> 0 | J85: 0 | K85: =J85*C85 -> 0 | L85: 0 | M85: =L85*C85 -> 0 | N85: 0 | O85: =N85*C85 -> 0 | P85: 10 | Q85: =P85*C85 -> 180000 | R85: 10 | S85: =R85*C85 -> 180000 | T85: 10 | U85: =T85*C85 -> 180000 | V85: 10 | W85: =V85*C85 -> 180000 | X85: 10 | Y85: =X85*C85 -> 180000 | Z85: 10 | AA85: =Z85*C85 -> 180000
A86: Certain Project condo | B86: 33 | C86: 30000 | D86: 0 | E86: =D86*C86 -> 0 | F86: 0 | G86: =F86*C86 -> 0 | H86: 0 | I86: =H86*C86 -> 0 | J86: 0 | K86: =J86*C86 -> 0 | L86: 0 | M86: =L86*C86 -> 0 | N86: 0 | O86: =N86*C86 -> 0 | P86: 5 | Q86: =P86*C86 -> 150000 | R86: 5 | S86: =R86*C86 -> 150000 | T86: 5 | U86: =T86*C86 -> 150000 | V86: 5 | W86: =V86*C86 -> 150000 | X86: 5 | Y86: =X86*C86 -> 150000 | Z86: 5 | AA86: =Z86*C86 -> 150000
A87: Certain Project condo | B87: 64 | C87: 60000 | D87: 0 | E87: =D87*C87 -> 0 | F87: 0 | G87: =F87*C87 -> 0 | H87: 0 | I87: =H87*C87 -> 0 | J87: 0 | K87: =J87*C87 -> 0 | L87: 0 | M87: =L87*C87 -> 0 | N87: 0 | O87: =N87*C87 -> 0 | P87: 2 | Q87: =P87*C87 -> 120000 | R87: 2 | S87: =R87*C87 -> 120000 | T87: 2 | U87: =T87*C87 -> 120000 | V87: 2 | W87: =V87*C87 -> 120000 | X87: 2 | Y87: =X87*C87 -> 120000 | Z87: 2 | AA87: =Z87*C87 -> 120000
A88: Certain Project condo | B88: 100 | C88: 80000 | D88: 0 | E88: =D88*C88 -> 0 | F88: 0 | G88: =F88*C88 -> 0 | H88: 0 | I88: =H88*C88 -> 0 | J88: 0 | K88: =J88*C88 -> 0 | L88: 0 | M88: =L88*C88 -> 0 | N88: 0 | O88: =N88*C88 -> 0 | P88: 0 | Q88: =P88*C88 -> 0 | R88: 0 | S88: =R88*C88 -> 0 | T88: 0 | U88: =T88*C88 -> 0 | V88: 0 | W88: =V88*C88 -> 0 | X88: 0 | Y88: =X88*C88 -> 0 | Z88: 0 | AA88: =Z88*C88 -> 0
A90: Certain Project House | B90: 150 | C90: 120000 | D90: 0 | E90: =D90*C90 -> 0 | F90: 0 | G90: =F90*C90 -> 0 | H90: 0 | I90: =H90*C90 -> 0 | J90: 0 | K90: =J90*C90 -> 0 | L90: 0 | M90: =L90*C90 -> 0 | N90: 0 | O90: =N90*C90 -> 0 | P90: 10 | Q90: =P90*C90 -> 1200000 | R90: 10 | S90: =R90*C90 -> 1200000 | T90: 10 | U90: =T90*C90 -> 1200000 | V90: 10 | W90: =V90*C90 -> 1200000 | X90: 10 | Y90: =X90*C90 -> 1200000 | Z90: 10 | AA90: =Z90*C90 -> 1200000
A91: Certain Project House | B91: 250 | C91: 200000 | D91: 0 | E91: =D91*C91 -> 0 | F91: 0 | G91: =F91*C91 -> 0 | H91: 0 | I91: =H91*C91 -> 0 | J91: 0 | K91: =J91*C91 -> 0 | L91: 0 | M91: =L91*C91 -> 0 | N91: 0 | O91: =N91*C91 -> 0 | P91: 5 | Q91: =P91*C91 -> 1000000 | R91: 5 | S91: =R91*C91 -> 1000000 | T91: 5 | U91: =T91*C91 -> 1000000 | V91: 5 | W91: =V91*C91 -> 1000000 | X91: 5 | Y91: =X91*C91 -> 1000000 | Z91: 5 | AA91: =Z91*C91 -> 1000000
A92: Certain Project House | B92: 350 | C92: 270000 | D92: 0 | E92: =D92*C92 -> 0 | F92: 0 | G92: =F92*C92 -> 0 | H92: 0 | I92: =H92*C92 -> 0 | J92: 0 | K92: =J92*C92 -> 0 | L92: 0 | M92: =L92*C92 -> 0 | N92: 0 | O92: =N92*C92 -> 0 | P92: 2 | Q92: =P92*C92 -> 540000 | R92: 2 | S92: =R92*C92 -> 540000 | T92: 2 | U92: =T92*C92 -> 540000 | V92: 2 | W92: =V92*C92 -> 540000 | X92: 2 | Y92: =X92*C92 -> 540000 | Z92: 2 | AA92: =Z92*C92 -> 540000
A93: Certain Project House | B93: 500 | C93: 350000 | D93: 0 | E93: =D93*C93 -> 0 | F93: 0 | G93: =F93*C93 -> 0 | H93: 0 | I93: =H93*C93 -> 0 | J93: 0 | K93: =J93*C93 -> 0 | L93: 0 | M93: =L93*C93 -> 0 | N93: 0 | O93: =N93*C93 -> 0 | P93: 0 | Q93: =P93*C93 -> 0 | R93: 0 | S93: =R93*C93 -> 0 | T93: 0 | U93: =T93*C93 -> 0 | V93: 0 | W93: =V93*C93 -> 0 | X93: 0 | Y93: =X93*C93 -> 0 | Z93: 0 | AA93: =Z93*C93 -> 0
A95: Certain Project Shop | B95: 100 | D95: 0 | E95: =D95*C95 -> 0 | F95: 0 | G95: =F95*C95 -> 0 | H95: 0 | I95: =H95*C95 -> 0 | J95: 0 | K95: =J95*C95 -> 0 | L95: 0 | M95: =L95*C95 -> 0 | N95: 0 | O95: =N95*C95 -> 0 | P95: 5 | Q95: =P95*C95 -> 0 | R95: 5 | S95: =R95*C95 -> 0 | T95: 5 | U95: =T95*C95 -> 0 | V95: 5 | W95: =V95*C95 -> 0 | X95: 5 | Y95: =X95*C95 -> 0 | Z95: 5 | AA95: =Z95*C95 -> 0
A96: Certain Project Shop | B96: 150 | D96: 0 | E96: =D96*C96 -> 0 | F96: 0 | G96: =F96*C96 -> 0 | H96: 0 | I96: =H96*C96 -> 0 | J96: 0 | K96: =J96*C96 -> 0 | L96: 0 | M96: =L96*C96 -> 0 | N96: 0 | O96: =N96*C96 -> 0 | P96: 4 | Q96: =P96*C96 -> 0 | R96: 4 | S96: =R96*C96 -> 0 | T96: 4 | U96: =T96*C96 -> 0 | V96: 4 | W96: =V96*C96 -> 0 | X96: 4 | Y96: =X96*C96 -> 0 | Z96: 4 | AA96: =Z96*C96 -> 0
A97: Certain Project Shop | B97: 250 | D97: 0 | E97: =D97*C97 -> 0 | F97: 0 | G97: =F97*C97 -> 0 | H97: 0 | I97: =H97*C97 -> 0 | J97: 0 | K97: =J97*C97 -> 0 | L97: 0 | M97: =L97*C97 -> 0 | N97: 0 | O97: =N97*C97 -> 0 | P97: 3 | Q97: =P97*C97 -> 0 | R97: 3 | S97: =R97*C97 -> 0 | T97: 3 | U97: =T97*C97 -> 0 | V97: 3 | W97: =V97*C97 -> 0 | X97: 3 | Y97: =X97*C97 -> 0 | Z97: 3 | AA97: =Z97*C97 -> 0
A98: Certain Project Shop | B98: 350 | D98: 0 | E98: =D98*C98 -> 0 | F98: 0 | G98: =F98*C98 -> 0 | H98: 0 | I98: =H98*C98 -> 0 | J98: 0 | K98: =J98*C98 -> 0 | L98: 0 | M98: =L98*C98 -> 0 | N98: 0 | O98: =N98*C98 -> 0 | P98: 3 | Q98: =P98*C98 -> 0 | R98: 3 | S98: =R98*C98 -> 0 | T98: 3 | U98: =T98*C98 -> 0 | V98: 3 | W98: =V98*C98 -> 0 | X98: 3 | Y98: =X98*C98 -> 0 | Z98: 3 | AA98: =Z98*C98 -> 0
A99: Certain Project Shop | B99: 500 | D99: 0 | E99: =D99*C99 -> 0 | F99: 0 | G99: =F99*C99 -> 0 | H99: 0 | I99: =H99*C99 -> 0 | J99: 0 | K99: =J99*C99 -> 0 | L99: 0 | M99: =L99*C99 -> 0 | N99: 0 | O99: =N99*C99 -> 0 | P99: 1 | Q99: =P99*C99 -> 0 | R99: 1 | S99: =R99*C99 -> 0 | T99: 1 | U99: =T99*C99 -> 0 | V99: 1 | W99: =V99*C99 -> 0 | X99: 1 | Y99: =X99*C99 -> 0 | Z99: 1 | AA99: =Z99*C99 -> 0
A101: Certain Project office | B101: 100 | C101: 80000 | D101: 0 | E101: =D101*C101 -> 0 | F101: 0 | G101: =F101*C101 -> 0 | H101: 0 | I101: =H101*C101 -> 0 | J101: 0 | K101: =J101*C101 -> 0 | L101: 0 | M101: =L101*C101 -> 0 | N101: 0 | O101: =N101*C101 -> 0 | P101: 5 | Q101: =P101*C101 -> 400000 | R101: 5 | S101: =R101*C101 -> 400000 | T101: 5 | U101: =T101*C101 -> 400000 | V101: 5 | W101: =V101*C101 -> 400000 | X101: 5 | Y101: =X101*C101 -> 400000 | Z101: 5 | AA101: =Z101*C101 -> 400000
A102: Certain Project office | B102: 150 | C102: 120000 | D102: 0 | E102: =D102*C102 -> 0 | F102: 0 | G102: =F102*C102 -> 0 | H102: 0 | I102: =H102*C102 -> 0 | J102: 0 | K102: =J102*C102 -> 0 | L102: 0 | M102: =L102*C102 -> 0 | N102: 0 | O102: =N102*C102 -> 0 | P102: 4 | Q102: =P102*C102 -> 480000 | R102: 4 | S102: =R102*C102 -> 480000 | T102: 4 | U102: =T102*C102 -> 480000 | V102: 4 | W102: =V102*C102 -> 480000 | X102: 4 | Y102: =X102*C102 -> 480000 | Z102: 4 | AA102: =Z102*C102 -> 480000
A103: Certain Project office | B103: 250 | C103: 200000 | D103: 0 | E103: =D103*C103 -> 0 | F103: 0 | G103: =F103*C103 -> 0 | H103: 0 | I103: =H103*C103 -> 0 | J103: 0 | K103: =J103*C103 -> 0 | L103: 0 | M103: =L103*C103 -> 0 | N103: 0 | O103: =N103*C103 -> 0 | P103: 3 | Q103: =P103*C103 -> 600000 | R103: 3 | S103: =R103*C103 -> 600000 | T103: 3 | U103: =T103*C103 -> 600000 | V103: 3 | W103: =V103*C103 -> 600000 | X103: 3 | Y103: =X103*C103 -> 600000 | Z103: 3 | AA103: =Z103*C103 -> 600000
A104: Certain Project office | B104: 350 | C104: 270000 | D104: 0 | E104: =D104*C104 -> 0 | F104: 0 | G104: =F104*C104 -> 0 | H104: 0 | I104: =H104*C104 -> 0 | J104: 0 | K104: =J104*C104 -> 0 | L104: 0 | M104: =L104*C104 -> 0 | N104: 0 | O104: =N104*C104 -> 0 | P104: 3 | Q104: =P104*C104 -> 810000 | R104: 3 | S104: =R104*C104 -> 810000 | T104: 3 | U104: =T104*C104 -> 810000 | V104: 3 | W104: =V104*C104 -> 810000 | X104: 3 | Y104: =X104*C104 -> 810000 | Z104: 3 | AA104: =Z104*C104 -> 810000
A105: Certain Project office | B105: 500 | C105: 350000 | D105: 0 | E105: =D105*C105 -> 0 | F105: 0 | G105: =F105*C105 -> 0 | H105: 0 | I105: =H105*C105 -> 0 | J105: 0 | K105: =J105*C105 -> 0 | L105: 0 | M105: =C105*L105 -> 0 | N105: 0 | O105: =N105*C105 -> 0 | P105: 1 | Q105: =P105*C105 -> 350000 | R105: 1 | S105: =R105*C105 -> 350000 | T105: 1 | U105: =T105*C105 -> 350000 | V105: 1 | W105: =V105*C105 -> 350000 | X105: 1 | Y105: =X105*C105 -> 350000 | Z105: 1 | AA105: =Z105*C105 -> 350000
D107: 0.1 | E107: =SUM(E85:E105) -> 0 | F107: 0.1 | G107: =SUM(G85:G105) -> 0 | H107: 0.1 | I107: =SUM(I85:I105) -> 0 | J107: 0.1 | K107: =SUM(K85:K105) -> 0 | L107: 0.1 | M107: =SUM(M85:M105) -> 0 | N107: 0.1 | O107: =SUM(O85:O105) -> 0 | P107: 0.05 | Q107: =SUM(Q85:Q105) -> 5830000 | R107: 0.05 | S107: =SUM(S85:S105) -> 5830000 | T107: 0.05 | U107: =SUM(U85:U105) -> 5830000 | V107: 0.05 | W107: =SUM(W85:W105) -> 5830000 | X107: 0.05 | Y107: =SUM(Y85:Y105) -> 5830000 | Z107: 0.05 | AA107: =SUM(AA85:AA105) -> 5830000
E108: =E107*D107 -> 0 | G108: =G107*F107 -> 0 | I108: =I107*H107 -> 0 | K108: =K107*J107 -> 0 | M108: =M107*L107 -> 0 | O108: =O107*N107 -> 0 | Q108: =Q107*P107 -> 291500 | S108: =S107*R107 -> 291500 | U108: =U107*T107 -> 291500 | W108: =W107*V107 -> 291500 | Y108: =Y107*X107 -> 291500 | AA108: =AA107*Z107 -> 291500 | AB108: =SUM(AA108,Y108,W108,U108,S108,Q108,O108,M108,K108,I108,G108,E108) -> 1749000
A110: Loose Furniture Project condo | B110: 26 | C110: 25000 | D110: 0 | E110: =D110*C110 -> 0 | F110: 0 | G110: =F110*C110 -> 0 | H110: 0 | I110: =H110*C110 -> 0 | J110: 0 | K110: =J110*C110 -> 0 | L110: 0 | M110: =L110*C110 -> 0 | N110: 0 | O110: =N110*C110 -> 0 | P110: 10 | Q110: =P110*C110 -> 250000 | R110: 10 | S110: =R110*C110 -> 250000 | T110: 10 | U110: =T110*C110 -> 250000 | V110: 10 | W110: =V110*C110 -> 250000 | X110: 10 | Y110: =X110*C110 -> 250000 | Z110: 10 | AA110: =Z110*C110 -> 250000
A111: Loose Furniture Project condo | B111: 33 | C111: 45000 | D111: 0 | E111: =D111*C111 -> 0 | F111: 0 | G111: =F111*C111 -> 0 | H111: 0 | I111: =H111*C111 -> 0 | J111: 0 | K111: =J111*C111 -> 0 | L111: 0 | M111: =L111*C111 -> 0 | N111: 0 | O111: =N111*C111 -> 0 | P111: 5 | Q111: =P111*C111 -> 225000 | R111: 5 | S111: =R111*C111 -> 225000 | T111: 5 | U111: =T111*C111 -> 225000 | V111: 5 | W111: =V111*C111 -> 225000 | X111: 5 | Y111: =X111*C111 -> 225000 | Z111: 5 | AA111: =Z111*C111 -> 225000
A112: Loose Furniture Project condo | B112: 64 | C112: 85000 | D112: 0 | E112: =D112*C112 -> 0 | F112: 0 | G112: =F112*C112 -> 0 | H112: 0 | I112: =H112*C112 -> 0 | J112: 0 | K112: =J112*C112 -> 0 | L112: 0 | M112: =L112*C112 -> 0 | N112: 0 | O112: =N112*C112 -> 0 | P112: 2 | Q112: =P112*C112 -> 170000 | R112: 2 | S112: =R112*C112 -> 170000 | T112: 2 | U112: =T112*C112 -> 170000 | V112: 2 | W112: =V112*C112 -> 170000 | X112: 2 | Y112: =X112*C112 -> 170000 | Z112: 2 | AA112: =Z112*C112 -> 170000
A113: Loose Furniture Project condo | B113: 100 | C113: 120000 | D113: 0 | E113: =D113*C113 -> 0 | F113: 0 | G113: =F113*C113 -> 0 | H113: 0 | I113: =H113*C113 -> 0 | J113: 0 | K113: =J113*C113 -> 0 | L113: 0 | M113: =L113*C113 -> 0 | N113: 0 | O113: =N113*C113 -> 0 | P113: 0 | Q113: =P113*C113 -> 0 | R113: 0 | S113: =R113*C113 -> 0 | T113: 0 | U113: =T113*C113 -> 0 | V113: 0 | W113: =V113*C113 -> 0 | X113: 0 | Y113: =X113*C113 -> 0 | Z113: 0 | AA113: =Z113*C113 -> 0
A115: Loose Furniture Project House | B115: 150 | C115: 150000 | D115: 0 | E115: =D115*C115 -> 0 | F115: 0 | G115: =F115*C115 -> 0 | H115: 0 | I115: =H115*C115 -> 0 | J115: 0 | K115: =J115*C115 -> 0 | L115: 0 | M115: =L115*C115 -> 0 | N115: 0 | O115: =N115*C115 -> 0 | P115: 10 | Q115: =P115*C115 -> 1500000 | R115: 10 | S115: =R115*C115 -> 1500000 | T115: 10 | U115: =T115*C115 -> 1500000 | V115: 10 | W115: =V115*C115 -> 1500000 | X115: 10 | Y115: =X115*C115 -> 1500000 | Z115: 10 | AA115: =Z115*C115 -> 1500000
A116: Loose Furniture Project House | B116: 250 | C116: 250000 | D116: 0 | E116: =D116*C116 -> 0 | F116: 0 | G116: =F116*C116 -> 0 | H116: 0 | I116: =H116*C116 -> 0 | J116: 0 | K116: =J116*C116 -> 0 | L116: 0 | M116: =L116*C116 -> 0 | N116: 0 | O116: =N116*C116 -> 0 | P116: 5 | Q116: =P116*C116 -> 1250000 | R116: 5 | S116: =R116*C116 -> 1250000 | T116: 5 | U116: =T116*C116 -> 1250000 | V116: 5 | W116: =V116*C116 -> 1250000 | X116: 5 | Y116: =X116*C116 -> 1250000 | Z116: 5 | AA116: =Z116*C116 -> 1250000
A117: Loose Furniture Project House | B117: 350 | C117: 320000 | D117: 0 | E117: =D117*C117 -> 0 | F117: 0 | G117: =F117*C117 -> 0 | H117: 0 | I117: =H117*C117 -> 0 | J117: 0 | K117: =J117*C117 -> 0 | L117: 0 | M117: =L117*C117 -> 0 | N117: 0 | O117: =N117*C117 -> 0 | P117: 2 | Q117: =P117*C117 -> 640000 | R117: 2 | S117: =R117*C117 -> 640000 | T117: 2 | U117: =T117*C117 -> 640000 | V117: 2 | W117: =V117*C117 -> 640000 | X117: 2 | Y117: =X117*C117 -> 640000 | Z117: 2 | AA117: =Z117*C117 -> 640000
A118: Loose Furniture Project House | B118: 500 | C118: 480000 | D118: 0 | E118: =D118*C118 -> 0 | F118: 0 | G118: =F118*C118 -> 0 | H118: 0 | I118: =H118*C118 -> 0 | J118: 0 | K118: =J118*C118 -> 0 | L118: 0 | M118: =L118*C118 -> 0 | N118: 0 | O118: =N118*C118 -> 0 | P118: 0 | Q118: =P118*C118 -> 0 | R118: 0 | S118: =R118*C118 -> 0 | T118: 0 | U118: =T118*C118 -> 0 | V118: 0 | W118: =V118*C118 -> 0 | X118: 0 | Y118: =X118*C118 -> 0 | Z118: 0 | AA118: =Z118*C118 -> 0
A120: Loose Furniture Project Shop | B120: 100 | C120: 120000 | D120: 0 | E120: =D120*C120 -> 0 | F120: 0 | G120: =F120*C120 -> 0 | H120: 0 | I120: =H120*C120 -> 0 | J120: 0 | K120: =J120*C120 -> 0 | L120: 0 | M120: =L120*C120 -> 0 | N120: 0 | O120: =N120*C120 -> 0 | P120: 5 | Q120: =P120*C120 -> 600000 | R120: 5 | S120: =R120*C120 -> 600000 | T120: 5 | U120: =T120*C120 -> 600000 | V120: 5 | W120: =V120*C120 -> 600000 | X120: 5 | Y120: =X120*C120 -> 600000 | Z120: 5 | AA120: =Z120*C120 -> 600000
A121: Loose Furniture Project Shop | B121: 150 | C121: 150000 | D121: 0 | E121: =D121*C121 -> 0 | F121: 0 | G121: =F121*C121 -> 0 | H121: 0 | I121: =H121*C121 -> 0 | J121: 0 | K121: =J121*C121 -> 0 | L121: 0 | M121: =L121*C121 -> 0 | N121: 0 | O121: =N121*C121 -> 0 | P121: 4 | Q121: =P121*C121 -> 600000 | R121: 4 | S121: =R121*C121 -> 600000 | T121: 4 | U121: =T121*C121 -> 600000 | V121: 4 | W121: =V121*C121 -> 600000 | X121: 4 | Y121: =X121*C121 -> 600000 | Z121: 4 | AA121: =Z121*C121 -> 600000
A122: Loose Furniture Project Shop | B122: 250 | C122: 250000 | D122: 0 | E122: =D122*C122 -> 0 | F122: 0 | G122: =F122*C122 -> 0 | H122: 0 | I122: =H122*C122 -> 0 | J122: 0 | K122: =J122*C122 -> 0 | L122: 0 | M122: =L122*C122 -> 0 | N122: 0 | O122: =N122*C122 -> 0 | P122: 3 | Q122: =P122*C122 -> 750000 | R122: 3 | S122: =R122*C122 -> 750000 | T122: 3 | U122: =T122*C122 -> 750000 | V122: 3 | W122: =V122*C122 -> 750000 | X122: 3 | Y122: =X122*C122 -> 750000 | Z122: 3 | AA122: =Z122*C122 -> 750000
...

Sheet Infrastructure (Direct Cost)
A1: Infrastructure
A2: Year1
A3: CATEGORY | B3: 43586 | C3: 43617 | D3: 43647 | E3: 43678 | F3: 43709 | G3: 43739 | H3: 43770 | I3: 43800 | J3: 43831 | K3: 43862 | L3: 43891 | M3: 43922 | N3: Total
A11: Year2
A12: CATEGORY | B12: 43952 | C12: 43983 | D12: 44013 | E12: 44044 | F12: 44075 | G12: 44105 | H12: 44136 | I12: 44166 | J12: 44197 | K12: 44228 | L12: 44256 | M12: 44287 | N12: Total
A20: Year3
A21: CATEGORY | B21: 44317 | C21: 44348 | D21: 44378 | E21: 44409 | F21: 44440 | G21: 44470 | H21: 44501 | I21: 44531 | J21: 44562 | K21: 44593 | L21: 44621 | M21: 44652 | N21: Total
A31: Year1 | B31: =SUM(B5:B10) -> 0 | C31: =SUM(C5:C10) -> 0 | D31: =SUM(D5:D10) -> 0 | E31: =SUM(E5:E10) -> 0 | F31: =SUM(F5:F10) -> 0 | G31: =SUM(G5:G10) -> 0 | H31: =SUM(H5:H10) -> 0 | I31: =SUM(I5:I10) -> 0 | ... M31: =SUM(M5:M10) -> 0
A32: Year2 | B32: =SUM(B14:B19) -> 0 | C32: =SUM(C14:C19) -> 0 | D32: =SUM(D14:D19) -> 0 | E32: =SUM(E14:E19) -> 0 | F32: =SUM(F14:F19) -> 0 | G32: =SUM(G14:G19) -> 0 | H32: =SUM(H14:H19) -> 0 | I32: =SUM(I14:I19) -> 0 | ... M32: =SUM(M14:M19) -> 0
A33: Year3 | B33: =SUM(B23:B29) -> 0 | C33: =SUM(C23:C29) -> 0 | D33: =SUM(D23:D29) -> 0 | E33: =SUM(E23:E29) -> 0 | F33: =SUM(F23:F29) -> 0 | G33: =SUM(G23:G29) -> 0 | H33: =SUM(H23:H29) -> 0 | I33: =SUM(I23:I29) -> 0 | ... M33: =SUM(M23:M29) -> 0
A37: รายละเอียด Spec Infra

Sheet Developer (Direct Cost)
A1: Operation (IT Developer or Engineer)
A2: Year1
B3: Growth | C3: 43586 | D3: 43617 | E3: 43647 | F3: 43678 | G3: 43709 | H3: 43739 | I3: 43770 | J3: 43800 | K3: 43831 | L3: 43862 | M3: 43891 | N3: 43922 | O3: Total
A11: Year2
A12: CATEGORY | B12: Growth | C12: 43952 | D12: 43983 | E12: 44013 | F12: 44044 | G12: 44075 | H12: 44105 | I12: 44136 | J12: 44166 | K12: 44197 | L12: 44228 | M12: 44256 | N12: 44287 | O12: Total
A20: Year3
A21: CATEGORY | B21: Growth | C21: 44317 | D21: 44348 | E21: 44378 | F21: 44409 | G21: 44440 | H21: 44470 | I21: 44501 | J21: 44531 | K21: 44562 | L21: 44593 | M21: 44621 | N21: 44652 | O21: Total
A31: Year1 | C31: =SUM(C5:C10) -> 0 | D31: =SUM(D5:D10) -> 0 | E31: =SUM(E5:E10) -> 0 | F31: =SUM(F5:F10) -> 0 | G31: =SUM(G5:G10) -> 0 | H31: =SUM(H5:H10) -> 0 | I31: =SUM(I5:I10) -> 0 | J31: =SUM(J5:J10) -> 0 | ... N31: =SUM(N5:N10) -> 0
A32: Year2 | C32: =SUM(C14:C19) -> 0 | D32: =SUM(D14:D19) -> 0 | E32: =SUM(E14:E19) -> 0 | F32: =SUM(F14:F19) -> 0 | G32: =SUM(G14:G19) -> 0 | H32: =SUM(H14:H19) -> 0 | I32: =SUM(I14:I19) -> 0 | J32: =SUM(J14:J19) -> 0 | ... N32: =SUM(N14:N19) -> 0
A33: Year3 | C33: =SUM(C23:C29) -> 0 | D33: =SUM(D23:D29) -> 0 | E33: =SUM(E23:E29) -> 0 | F33: =SUM(F23:F29) -> 0 | G33: =SUM(G23:G29) -> 0 | H33: =SUM(H23:H29) -> 0 | I33: =SUM(I23:I29) -> 0 | J33: =SUM(J23:J29) -> 0 | ... N33: =SUM(N23:N29) -> 0

Sheet Marketing (SGA)
A1: Marketing
A2: Year 1
A3: CATEGORY | E3: 43831 | G3: 43862 | I3: 43891 | K3: 43922 | M3: 43952 | O3: 43983 | Q3: 44013 | S3: 44044 | U3: 44075 | W3: 44105 | Y3: 44136 | AA3: 44166 | AB3: Total
A5: Google ad | G5: 100000 | I5: 100000 | K5: 100000 | M5: 100000 | O5: 100000 | Q5: 100000 | S5: 600000 | U5: 600000 | W5: 600000 | Y5: 600000 | AA5: 600000
A6: facebook | G6: 600000 | I6: 600000 | K6: 600000 | M6: 600000 | O6: 600000 | Q6: 600000 | S6: 2500000 | U6: 2500000 | W6: 2500000 | Y6: 2500000 | AA6: 2500000
A7: Blog | G7: 200000 | I7: 200000 | K7: 200000 | M7: 200000 | O7: 200000 | Q7: 200000 | S7: 600000 | U7: 600000 | W7: 600000 | Y7: 600000 | AA7: 600000
A8: youtub | S8: 2000000 | U8: 2000000 | W8: 2000000 | Y8: 2000000 | AA8: 2000000
A10: Architecture Expo | I10: 2500000
A11: บ้านและสวนแฟร์ | G11: 500000 | S11: 500000 | W11: 500000
A12: Event | AB12: =SUM(E12:AA12) -> 0
A13: Interior Company Visit | G13: 125000 | I13: 125000 | K13: 125000 | M13: 125000 | O13: 125000 | Q13: 125000 | S13: 125000 | U13: 125000 | W13: 125000 | Y13: 125000 | AA13: 125000 | AB13: =SUM(AA13,Y13,W13,U13,S13,Q13,O13,M13,K13,I13,G13,E13) -> 1375000
A14: Interior and Decorate Shop | G14: 125000 | I14: 125000 | K14: 125000 | M14: 125000 | O14: 125000 | Q14: 125000 | S14: 125000 | U14: 125000 | W14: 125000 | Y14: 125000 | AA14: 125000 | AB14: =SUM(AA14,Y14,W14,U14,S14,Q14,O14,M14,K14,I14,G14,E14) -> 1375000
A15: Billboard
A16: Department Store Event
A17: สัมมนา
E18: =SUM(E5:E17) -> 0 | G18: =SUM(G5:G17) -> 1650000 | I18: =SUM(I5:I17) -> 3650000 | K18: =SUM(K5:K17) -> 1150000 | M18: =SUM(M5:M17) -> 1150000 | O18: =SUM(O5:O17) -> 1150000 | Q18: =SUM(Q5:Q17) -> 1150000 | S18: =SUM(S5:S17) -> 6450000 | U18: =SUM(U5:U17) -> 5950000 | W18: =SUM(W5:W17) -> 6450000 | Y18: =SUM(Y5:Y17) -> 5950000 | AA18: =SUM(AA5:AA17) -> 5950000 | AB18: =SUM(AA18,Y18,W18,U18,S18,Q18,O18,M18,K18,I18,G18,E18) -> 40650000
A20: Year 2
A21: CATEGORY | E21: 43831 | G21: 43862 | I21: 43891 | K21: 43922 | M21: 43952 | O21: 43983 | Q21: 44013 | S21: 44044 | U21: 44075 | W21: 44105 | Y21: 44136 | AA21: 44166 | AB21: Total
A23: Google ad | E23: 600000 | G23: 600000 | I23: 600000 | K23: 600000 | M23: 600000 | O23: 600000 | Q23: 1000000 | S23: 1000000 | U23: 1000000 | W23: 1000000 | Y23: 1000000 | AA23: 1000000
A24: facebook | E24: 8000000 | G24: 8000000 | I24: 8000000 | K24: 8000000 | M24: 8000000 | O24: 8000000 | Q24: 16000000 | S24: 16000000 | U24: 16000000 | W24: 16000000 | Y24: 16000000 | AA24: 16000000
A25: Blog | E25: 1000000 | G25: 1000000 | I25: 1000000 | K25: 1000000 | M25: 1000000 | O25: 1000000 | Q25: 3000000 | S25: 3000000 | U25: 3000000 | W25: 3000000 | Y25: 3000000 | AA25: 3000000
A26: youtub | E26: 6000000 | G26: 6000000 | I26: 6000000 | K26: 6000000 | M26: 6000000 | O26: 6000000 | Q26: 12000000 | S26: 12000000 | U26: 12000000 | W26: 12000000 | Y26: 12000000 | AA26: 12000000
A28: Architecture Expo | I28: 3500000
A29: บ้านและสวนแฟร์ | G29: 1000000 | S29: 1000000 | W29: 1000000
A30: Event | K30: 1500000 | U30: 1500000 | AA30: 5000000 | AB30: =SUM(E30:AA30) -> 8000000
A31: Interior Company Visit | G31: 125000 | I31: 125000 | K31: 125000 | M31: 125000 | O31: 125000 | Q31: 125000 | S31: 125000 | U31: 125000 | W31: 125000 | Y31: 125000 | AA31: 125000 | AB31: =SUM(AA31,Y31,W31,U31,S31,Q31,O31,M31,K31,I31,G31,E31) -> 1375000
A32: Interior and Decorate Shop | G32: 125000 | I32: 125000 | K32: 125000 | M32: 125000 | O32: 125000 | Q32: 125000 | S32: 125000 | U32: 125000 | W32: 125000 | Y32: 125000 | AA32: 125000 | AB32: =SUM(AA32,Y32,W32,U32,S32,Q32,O32,M32,K32,I32,G32,E32) -> 1375000
A33: Billboard | Q33: 1000000 | S33: 1000000 | U33: 1000000 | W33: 1000000 | Y33: 1000000 | AA33: 1000000
A35: สัมมนา
E36: =SUM(E23:E35) -> 15600000 | G36: =SUM(G23:G35) -> 16850000 | I36: =SUM(I23:I35) -> 19350000 | K36: =SUM(K23:K35) -> 17350000 | M36: =SUM(M23:M35) -> 15850000 | O36: =SUM(O23:O35) -> 15850000 | Q36: =SUM(Q23:Q35) -> 33250000 | S36: =SUM(S23:S35) -> 34250000 | U36: =SUM(U23:U35) -> 34750000 | W36: =SUM(W23:W35) -> 34250000 | Y36: =SUM(Y23:Y35) -> 33250000 | AA36: =SUM(AA23:AA35) -> 38250000 | AB36: =SUM(AA36,Y36,W36,U36,S36,Q36,O36,M36,K36,I36,G36,E36) -> 308850000
A37: Year 3
A38: CATEGORY | E38: 43831 | G38: 43862 | I38: 43891 | K38: 43922 | M38: 43952 | O38: 43983 | Q38: 44013 | S38: 44044 | U38: 44075 | W38: 44105 | Y38: 44136 | AA38: 44166 | AB38: Total
A40: Google ad | E40: 1000000 | G40: 1000000 | I40: 1000000 | K40: 1000000 | M40: 1000000 | O40: 1000000 | Q40: 1000000 | S40: 1000000 | U40: 1000000 | W40: 1000000 | Y40: 1000000 | AA40: 1000000
A41: facebook | E41: 30000000 | G41: 30000000 | I41: 30000000 | K41: 30000000 | M41: 30000000 | O41: 30000000 | Q41: 30000000 | S41: 30000000 | U41: 30000000 | W41: 30000000 | Y41: 30000000 | AA41: 30000000
A42: Blog | E42: 3000000 | G42: 3000000 | I42: 3000000 | K42: 3000000 | M42: 3000000 | O42: 3000000 | Q42: 3000000 | S42: 3000000 | U42: 3000000 | W42: 3000000 | Y42: 3000000 | AA42: 3000000
A43: youtub | E43: 24000000 | G43: 24000000 | I43: 24000000 | K43: 24000000 | M43: 24000000 | O43: 24000000 | Q43: 24000000 | S43: 24000000 | U43: 24000000 | W43: 24000000 | Y43: 24000000 | AA43: 24000000
A45: Architecture Expo | I45: 2500000
A46: บ้านและสวนแฟร์ | G46: 500000 | S46: 500000 | W46: 500000
A47: Event | K47: 1500000 | U47: 1500000 | AA47: 10000000 | AB47: =SUM(E47:AA47) -> 13000000
A48: Interior Company Visit | G48: 125000 | I48: 125000 | K48: 125000 | M48: 125000 | O48: 125000 | Q48: 125000 | S48: 125000 | U48: 125000 | W48: 125000 | Y48: 125000 | AA48: 125000 | AB48: =SUM(AA48,Y48,W48,U48,S48,Q48,O48,M48,K48,I48,G48,E48) -> 1375000
A49: Interior and Decorate Shop | G49: 125000 | I49: 125000 | K49: 125000 | M49: 125000 | O49: 125000 | Q49: 125000 | S49: 125000 | U49: 125000 | W49: 125000 | Y49: 125000 | AA49: 125000 | AB49: =SUM(AA49,Y49,W49,U49,S49,Q49,O49,M49,K49,I49,G49,E49) -> 1375000
A50: Billboard | E50: 2000000 | G50: 2000000 | I50: 2000000 | K50: 2000000 | M50: 2000000 | O50: 2000000 | Q50: 2000000 | S50: 2000000 | U50: 2000000 | W50: 2000000 | Y50: 2000000 | AA50: 2000000
A51: Department Store Event
A52: สัมมนา
E53: =SUM(E40:E52) -> 60000000 | G53: =SUM(G40:G52) -> 60750000 | I53: =SUM(I40:I52) -> 62750000 | K53: =SUM(K40:K52) -> 61750000 | M53: =SUM(M40:M52) -> 60250000 | O53: =SUM(O40:O52) -> 60250000 | Q53: =SUM(Q40:Q52) -> 60250000 | S53: =SUM(S40:S52) -> 60750000 | U53: =SUM(U40:U52) -> 61750000 | W53: =SUM(W40:W52) -> 60750000 | Y53: =SUM(Y40:Y52) -> 60250000 | AA53: =SUM(AA40:AA52) -> 70250000 | AB53: =SUM(AA53,Y53,W53,U53,S53,Q53,O53,M53,K53,I53,G53,E53) -> 739750000
A56: Year1 | B56: =SUM(#REF!) -> #REF! | C56: =SUM(#REF!) -> #REF! | D56: =SUM(#REF!) -> #REF! | E56: =SUM(#REF!) -> #REF! | F56: =SUM(#REF!) -> #REF! | G56: =SUM(#REF!) -> #REF! | H56: =SUM(#REF!) -> #REF! | I56: =SUM(#REF!) -> #REF! | ... M56: =SUM(#REF!) -> #REF!
A57: Year2 | B57: =SUM(#REF!) -> #REF! | C57: =SUM(#REF!) -> #REF! | D57: =SUM(#REF!) -> #REF! | E57: =SUM(#REF!) -> #REF! | F57: =SUM(#REF!) -> #REF! | G57: =SUM(#REF!) -> #REF! | H57: =SUM(#REF!) -> #REF! | I57: =SUM(#REF!) -> #REF! | ... M57: =SUM(#REF!) -> #REF!
A58: Year3 | B58: =SUM(#REF!) -> #REF! | C58: =SUM(#REF!) -> #REF! | D58: =SUM(#REF!) -> #REF! | E58: =SUM(#REF!) -> #REF! | F58: =SUM(#REF!) -> #REF! | G58: =SUM(#REF!) -> #REF! | H58: =SUM(#REF!) -> #REF! | I58: =SUM(#REF!) -> #REF! | ... M58: =SUM(#REF!) -> #REF!
C63: Google ad
C64: facebook
C65: Blog
C66: youtub
C68: Architecture Expo
C69: บ้านและสวนแฟร์
C70: University Booth
C71: Interior Company Visit
C72: Interior and Decorate Shop
C73: Billboard
C74: Department Store Event
C75: สัมมนา

Sheet Officer ( SGA) พนักงาน
C1: Officer
A2: Year1 | B2: Year1 | C2: Year1
E3: Growth | F3: 43831 | G3: 43862 | H3: 43891 | I3: 43922 | J3: 43952 | K3: 43983 | L3: 44013 | M3: 44044 | N3: 44075 | O3: 44105 | P3: 44136 | Q3: 44166 | R3: Total
B6: General Manager | C6: General Manager | D6: 1
B7: BD | C7: BD | D7: 1
B8: Sale officer | C8: Sale officer | D8: 4 | E8: 200 /4 per month | F8: 120000 | G8: 120000 | H8: 120000 | I8: 120000 | J8: 120000 | K8: 120000 | L8: 240000 | M8: 240000 | N8: 240000 | O8: 240000 | P8: 240000 | Q8: 240000
B10: Platform Support | D10: 1
D11: 2 | F11: 180000 | G11: 180000 | H11: 180000 | I11: 180000 | J11: 180000 | K11: 180000 | L11: 450000 | M11: 450000 | N11: 450000 | O11: 450000 | P11: 450000 | Q11: 450000
D12: 3
A17: Marketing | B17: Marketing | D17: 3
E19: 200 /per month | F19: 140000 | G19: 140000 | H19: 140000 | I19: 140000 | J19: 140000 | K19: 140000 | L19: 140000 | M19: 140000 | N19: 140000 | O19: 140000 | P19: 140000 | Q19: 140000
B24: digital marketing | D24: 6
E28: 200 /per month | F28: 220000 | G28: 220000 | H28: 220000 | I28: 220000 | J28: 220000 | K28: 220000 | L28: 220000 | M28: 220000 | N28: 220000 | O28: 220000 | P28: 220000 | Q28: 220000
B33: Production House | D33: 4 | E33: 200 /per month | F33: 120000 | G33: 120000 | H33: 120000 | I33: 120000 | J33: 120000 | K33: 120000 | L33: 240000 | M33: 240000 | N33: 240000 | O33: 240000 | P33: 240000 | Q33: 240000
D34: 2 | E34: 200 /per month | F34: 60000 | G34: 60000 | H34: 60000 | I34: 60000 | J34: 60000 | K34: 60000 | L34: 120000 | M34: 120000 | N34: 120000 | O34: 120000 | P34: 120000 | Q34: 120000
D35: 4 | E35: 200 /per month | F35: 120000 | G35: 120000 | H35: 120000 | I35: 120000 | J35: 120000 | K35: 120000 | L35: 240000 | M35: 240000 | N35: 240000 | O35: 240000 | P35: 240000 | Q35: 240000
D36: 1 | E36: 200 /per month | F36: 35000 | G36: 35000 | H36: 35000 | I36: 35000 | J36: 35000 | K36: 35000 | L36: 70000 | M36: 70000 | N36: 70000 | O36: 70000 | P36: 70000 | Q36: 70000
D37: 4 | E37: 200 /per month | F37: 100000 | G37: 100000 | H37: 100000 | I37: 100000 | J37: 100000 | K37: 100000 | L37: 200000 | M37: 200000 | N37: 200000 | O37: 200000 | P37: 200000 | Q37: 200000
D38: 4 | E38: 200 /per month | F38: 36000 | G38: 36000 | H38: 36000 | I38: 36000 | J38: 36000 | K38: 36000 | L38: 80000 | M38: 80000 | N38: 80000 | O38: 80000 | P38: 80000 | Q38: 80000
D39: 1 | E39: 200 /per month | F39: 28000 | G39: 28000 | H39: 28000 | I39: 28000 | J39: 28000 | K39: 28000 | L39: 50000 | M39: 50000 | N39: 50000 | O39: 50000 | P39: 50000 | Q39: 50000
D40: 4 | E40: 200 /per month | F40: 72000 | G40: 72000 | H40: 72000 | I40: 72000 | J40: 72000 | K40: 72000 | L40: 150000 | M40: 150000 | N40: 150000 | O40: 150000 | P40: 150000 | Q40: 150000
D41: 1 | E41: 200 /per month | F41: 55000 | G41: 55000 | H41: 55000 | I41: 55000 | J41: 55000 | K41: 55000 | L41: 120000 | M41: 120000 | N41: 120000 | O41: 120000 | P41: 120000 | Q41: 120000
A43: Software | B43: Project Design | C43: Develop Functional Specifications
C44: Develop System Architecture
C45: Develop Preliminary Design Specification
C46: Develop Detailed Design Specifications
C47: Develop Acceptance Test Plan
B49: System Development | C49: Develop Components
C50: Development Acceptance Test Package
C51: Perform Unit/Integration Test
B53: Project Management | C53: Internal Status Meetings/Reports
C54: Configuration Management
C55: Quality Assurance
C56: Overall Project Management
B58: Test and Delivery | C58: Install System
C59: Train Customers
C60: Perform Acceptance Test
C61: Perform Post Project Review
C62: Achieve Materials
B64: Infarstructuer | C64: On-Clound Server
F66: =SUM(F6:F64) -> 1286000 | G66: =SUM(G6:G64) -> 1286000 | H66: =SUM(G6:G64) -> 1286000 | I66: =SUM(I6:I64) -> 1286000 | J66: =SUM(J6:J64) -> 1286000 | K66: =SUM(K6:K64) -> 1286000 | L66: =SUM(L6:L64) -> 2320000 | M66: =SUM(M6:M64) -> 2320000 | N66: =SUM(N7:N64) -> 2320000 | O66: =SUM(O6:O64) -> 2320000 | P66: =SUM(P6:P64) -> 2320000 | Q66: =SUM(Q6:Q64) -> 2320000 | R66: =SUM(H66:Q66,G66,F66) -> 21636000
A68: Year2 | B68: Year2 | C68: Year2
E69: Growth | F69: 43831 | G69: 43862 | H69: 43891 | I69: 43922 | J69: 43952 | K69: 43983 | L69: 44013 | M69: 44044 | N69: 44075 | O69: 44105 | P69: 44136 | Q69: 44166 | R69: Total
B72: General Manager | C72: General Manager
B73: BD | C73: BD
B74: Sale officer | C74: Sale officer | F74: 500000 | G74: 500000 | H74: 500000 | I74: 500000 | J74: 500000 | K74: 500000 | L74: 1000000 | M74: 1000000 | N74: 1000000 | O74: 1000000 | P74: 1000000 | Q74: 1000000
B76: Platform Support
F77: 600000 | G77: 600000 | H77: 600000 | I77: 600000 | J77: 600000 | K77: 600000 | L77: 1200000 | M77: 1200000 | N77: 1200000 | O77: 1200000 | P77: 1200000 | Q77: 1200000
A83: Marketing | B83: Marketing
F85: 500000 | G85: 500000 | H85: 500000 | I85: 500000 | J85: 500000 | K85: 500000 | L85: 1000000 | M85: 1000000 | N85: 1000000 | O85: 1000000 | P85: 1000000 | Q85: 1000000
B90: digital marketing
F94: 1000000 | G94: 1000000 | H94: 1000000 | I94: 1000000 | J94: 1000000 | K94: 1000000 | L94: 1000000 | M94: 1000000 | N94: 1000000 | O94: 1000000 | P94: 1000000 | Q94: 1000000
B99: Production House | F99: 400000 | G99: 400000 | H99: 400000 | I99: 400000 | J99: 400000 | K99: 400000 | L99: 800000 | M99: 800000 | N99: 800000 | O99: 800000 | P99: 800000 | Q99: 800000
F100: 200000 | G100: 200000 | H100: 200000 | I100: 200000 | J100: 200000 | K100: 200000 | L100: 250000 | M100: 250000 | N100: 250000 | O100: 250000 | P100: 250000 | Q100: 250000
F101: 400000 | G101: 400000 | H101: 400000 | I101: 400000 | J101: 400000 | K101: 400000 | L101: 800000 | M101: 800000 | N101: 800000 | O101: 800000 | P101: 800000 | Q101: 800000
F102: 100000 | G102: 100000 | H102: 100000 | I102: 100000 | J102: 100000 | K102: 100000 | L102: 150000 | M102: 150000 | N102: 150000 | O102: 150000 | P102: 150000 | Q102: 150000
F103: 300000 | G103: 300000 | H103: 300000 | I103: 300000 | J103: 300000 | K103: 300000 | L103: 600000 | M103: 600000 | N103: 600000 | O103: 600000 | P103: 600000 | Q103: 600000
F104: 100000 | G104: 100000 | H104: 100000 | I104: 100000 | J104: 100000 | K104: 100000 | L104: 200000 | M104: 200000 | N104: 200000 | O104: 200000 | P104: 200000 | Q104: 200000
F105: 80000 | G105: 80000 | H105: 80000 | I105: 80000 | J105: 80000 | K105: 80000 | L105: 160000 | M105: 160000 | N105: 160000 | O105: 160000 | P105: 160000 | Q105: 160000
F106: 280000 | G106: 280000 | H106: 280000 | I106: 280000 | J106: 280000 | K106: 280000 | L106: 550000 | M106: 550000 | N106: 550000 | O106: 550000 | P106: 550000 | Q106: 550000
F107: 150000 | G107: 150000 | H107: 150000 | I107: 150000 | J107: 150000 | K107: 150000 | L107: 300000 | M107: 300000 | N107: 300000 | O107: 300000 | P107: 300000 | Q107: 300000
A109: Software | B109: Project Design | C109: Develop Functional Specifications
C110: Develop System Architecture
C111: Develop Preliminary Design Specification
C112: Develop Detailed Design Specifications
C113: Develop Acceptance Test Plan
B115: System Development | C115: Develop Components
C116: Development Acceptance Test Package
C117: Perform Unit/Integration Test
B119: Project Management | C119: Internal Status Meetings/Reports
C120: Configuration Management
C121: Quality Assurance
C122: Overall Project Management
B124: Test and Delivery | C124: Install System
C125: Train Customers
C126: Perform Acceptance Test
C127: Perform Post Project Review
C128: Achieve Materials
B130: Infarstructuer | C130: On-Clound Server
F132: =SUM(F72:F130) -> 4610000 | G132: =SUM(G72:G130) -> 4610000 | H132: =SUM(G72:G130) -> 4610000 | I132: =SUM(I72:I130) -> 4610000 | J132: =SUM(J72:J130) -> 4610000 | K132: =SUM(K72:K130) -> 4610000 | L132: =SUM(L72:L130) -> 8010000 | M132: =SUM(M72:M130) -> 8010000 | N132: =SUM(N73:N130) -> 8010000 | O132: =SUM(O72:O130) -> 8010000 | P132: =SUM(P72:P130) -> 8010000 | Q132: =SUM(Q72:Q130) -> 8010000 | R132: =SUM(H132:Q132,G132,F132) -> 75720000
A133: Year3 | B133: Year3 | C133: Year3
E134: Growth | F134: 43831 | G134: 43862 | H134: 43891 | I134: 43922 | J134: 43952 | K134: 43983 | L134: 44013 | M134: 44044 | N134: 44075 | O134: 44105 | P134: 44136 | Q134: 44166 | R134: Total
B137: General Manager | C137: General Manager | D137: 1
B138: BD | C138: BD | D138: 1
B139: Sale officer | C139: Sale officer | D139: 4 | E139: 200 /4 per month | F139: 2000000 | G139: 2000000 | H139: 2000000 | I139: 2000000 | J139: 2000000 | K139: 2000000 | L139: 2000000 | M139: 2000000 | N139: 2000000 | O139: 2000000 | P139: 2000000 | Q139: 2000000
B141: Platform Support | D141: 1
D142: 2 | F142: 2400000 | G142: 2400000 | H142: 2400000 | I142: 2400000 | J142: 2400000 | K142: 2400000 | L142: 2400000 | M142: 2400000 | N142: 2400000 | O142: 2400000 | P142: 2400000 | Q142: 2400000
D143: 3
A148: Marketing | B148: Marketing | D148: 3
E150: 200 /per month | F150: 2000000 | G150: 2000000 | H150: 2000000 | I150: 2000000 | J150: 2000000 | K150: 2000000 | L150: 2000000 | M150: 2000000 | N150: 2000000 | O150: 2000000 | P150: 2000000 | Q150: 2000000
B155: digital marketing | D155: 6
E159: 200 /per month | F159: 2000000 | G159: 2000000 | H159: 2000000 | I159: 2000000 | J159: 2000000 | K159: 2000000 | L159: 2000000 | M159: 2000000 | N159: 2000000 | O159: 2000000 | P159: 2000000 | Q159: 2000000
B164: Production House | D164: 4 | E164: 200 /per month | F164: 2000000 | G164: 2000000 | H164: 2000000 | I164: 2000000 | J164: 2000000 | K164: 2000000 | L164: 2000000 | M164: 2000000 | N164: 2000000 | O164: 2000000 | P164: 2000000 | Q164: 2000000
D165: 2 | E165: 200 /per month | F165: 5000000 | G165: 5000000 | H165: 5000000 | I165: 5000000 | J165: 5000000 | K165: 5000000 | L165: 5000000 | M165: 5000000 | N165: 5000000 | O165: 5000000 | P165: 5000000 | Q165: 5000000
D166: 4 | E166: 200 /per month | F166: 2000000 | G166: 2000000 | H166: 2000000 | I166: 2000000 | J166: 2000000 | K166: 2000000 | L166: 2000000 | M166: 2000000 | N166: 2000000 | O166: 2000000 | P166: 2000000 | Q166: 2000000
D167: 1 | E167: 200 /per month | F167: 400000 | G167: 400000 | H167: 400000 | I167: 400000 | J167: 400000 | K167: 400000 | L167: 400000 | M167: 400000 | N167: 400000 | O167: 400000 | P167: 400000 | Q167: 400000
D168: 4 | E168: 200 /per month | F168: 1500000 | G168: 1500000 | H168: 1500000 | I168: 1500000 | J168: 1500000 | K168: 1500000 | L168: 1500000 | M168: 1500000 | N168: 1500000 | O168: 1500000 | P168: 1500000 | Q168: 1500000
D169: 4 | E169: 200 /per month | F169: 4000000 | G169: 4000000 | H169: 4000000 | I169: 4000000 | J169: 4000000 | K169: 4000000 | L169: 4000000 | M169: 4000000 | N169: 4000000 | O169: 4000000 | P169: 4000000 | Q169: 4000000
D170: 1 | E170: 200 /per month | F170: 350000 | G170: 350000 | H170: 350000 | I170: 350000 | J170: 350000 | K170: 350000 | L170: 350000 | M170: 350000 | N170: 350000 | O170: 350000 | P170: 350000 | Q170: 350000
D171: 4 | E171: 200 /per month | F171: 1500000 | G171: 1500000 | H171: 1500000 | I171: 1500000 | J171: 1500000 | K171: 1500000 | L171: 1500000 | M171: 1500000 | N171: 1500000 | O171: 1500000 | P171: 1500000 | Q171: 1500000
...

Sheet Other Expense (SGA)
A1: Other Expense
A2: Year1
A3: CATEGORY | B3: 43586 | C3: 43617 | D3: 43647 | E3: 43678 | F3: 43709 | G3: 43739 | H3: 43770 | I3: 43800 | J3: 43831 | K3: 43862 | L3: 43891 | M3: 43922 | N3: Total
A11: Year2
A12: CATEGORY | B12: 43952 | C12: 43983 | D12: 44013 | E12: 44044 | F12: 44075 | G12: 44105 | H12: 44136 | I12: 44166 | J12: 44197 | K12: 44228 | L12: 44256 | M12: 44287 | N12: Total
A20: Year3
A21: CATEGORY | B21: 44317 | C21: 44348 | D21: 44378 | E21: 44409 | F21: 44440 | G21: 44470 | H21: 44501 | I21: 44531 | J21: 44562 | K21: 44593 | L21: 44621 | M21: 44652 | N21: Total
A32: Year1 | B32: =SUM(B5:B10) -> 0 | C32: =SUM(C5:C10) -> 0 | D32: =SUM(D5:D10) -> 0 | E32: =SUM(E5:E10) -> 0 | F32: =SUM(F5:F10) -> 0 | G32: =SUM(G5:G10) -> 0 | H32: =SUM(H5:H10) -> 0 | I32: =SUM(I5:I10) -> 0 | ... M32: =SUM(M5:M10) -> 0
A33: Year2 | B33: =SUM(B14:B19) -> 0 | C33: =SUM(C14:C19) -> 0 | D33: =SUM(D14:D19) -> 0 | E33: =SUM(E14:E19) -> 0 | F33: =SUM(F14:F19) -> 0 | G33: =SUM(G14:G19) -> 0 | H33: =SUM(H14:H19) -> 0 | I33: =SUM(I14:I19) -> 0 | ... M33: =SUM(M14:M19) -> 0
A34: Year3 | B34: =SUM(B23:B29) -> 0 | C34: =SUM(C23:C29) -> 0 | D34: =SUM(D23:D29) -> 0 | E34: =SUM(E23:E29) -> 0 | F34: =SUM(F23:F29) -> 0 | G34: =SUM(G23:G29) -> 0 | H34: =SUM(H23:H29) -> 0 | I34: =SUM(I23:I29) -> 0 | ... M34: =SUM(M23:M29) -> 0

Sheet Summary Year (original)
B2: Original | C2: Year 1 | D2: Year 2 | E2: Year 3
B3: =REVENUE!A7 -> xxxx | C3: =REVENUE!AA7 -> 0 | D3: =REVENUE!AA288 -> 0 | E3: =REVENUE!#REF! -> #REF!
B4: =REVENUE!A8 -> 0 | C4: =REVENUE!AA281 -> 0 | D4: =REVENUE!AA289 -> 0 | E4: =REVENUE!AA577 -> 0
B5: =REVENUE!A281 -> 0 | C5: =REVENUE!AA281 -> 0 | D5: =REVENUE!AA290 -> 0 | E5: =REVENUE!AA592 -> 0
B8: P/L | C8: Year 1 | D8: Year 2 | E8: Year 3 | F8: Total | G8: %
B9: ='Budget Plan'!A20 -> Revenue | C9: =SUM(C11:C14) -> 0 | D9: =SUM(D11:D14) -> 0 | E9: =SUM(E11:E14) -> 0 | F9: =SUM(C9:E9) -> 0 | G9: =F9/$F$9 -> #DIV/0!
B10: Develop for INET
B11: ='Budget Plan'!A22 -> Revenue From sales | C11: =SUM('Budget Plan'!G22:R22) -> 0 | D11: =SUM('Budget Plan'!S22:AD22) -> 0 | E11: =SUM('Budget Plan'!AE22:AP22) -> 0 | F11: =SUM(C11:E11) -> 0 | G11: =F11/$F$9 -> #DIV/0!
B15: ='Budget Plan'!A28 -> Direct Cost | C15: =SUM(C16:C18) -> 0 | D15: =SUM(D16:D18) -> 0 | E15: =SUM(E16:E18) -> 0 | F15: =SUM(C15:E15) -> 0 | G15: =F15/$F$9 -> #DIV/0!
B16: ='Budget Plan'!A29 -> Onetime | C16: =SUM('Budget Plan'!G29:R29) -> 0 | D16: =SUM('Budget Plan'!S29:AD29) -> 0 | E16: =SUM('Budget Plan'!AE29:AP29) -> 0 | F16: =SUM(C16:E16) -> 0 | G16: =F16/$F$9 -> #DIV/0!
B17: ='Budget Plan'!A33 -> 0 | C17: =SUM('Budget Plan'!G33:R33) -> 0 | D17: =SUM('Budget Plan'!S33:AD33) -> 0 | E17: =SUM('Budget Plan'!AE33:AP33) -> 0 | F17: =SUM(C17:E17) -> 0 | G17: =F17/$F$9 -> #DIV/0!
B18: ='Budget Plan'!A50 -> Revenue Share | C18: =SUM('Budget Plan'!G50:R50) -> 0 | D18: =SUM('Budget Plan'!S50:AD50) -> 0 | E18: =SUM('Budget Plan'!AE50:AP50) -> 0 | F18: =SUM(C18:E18) -> 0 | G18: =F18/$F$9 -> #DIV/0!
B19: ='Budget Plan'!A53 -> Gross Profit | C19: =SUM('Budget Plan'!G53:R53) -> 0 | D19: =SUM('Budget Plan'!S53:AD53) -> 0 | E19: =SUM('Budget Plan'!AE53:AE53) -> 0 | F19: =SUM(C19:E19) -> 0 | G19: =F19/$F$9 -> #DIV/0!
B20: ='Budget Plan'!A54 -> SG&A | C20: =SUM('Budget Plan'!G54:R54) -> #REF! | D20: =SUM('Budget Plan'!S54:AD54) -> #REF! | E20: =SUM('Budget Plan'!AE54:AP54) -> #REF! | F20: =SUM(C20:E20) -> #REF! | G20: =F20/$F$9 -> #REF!
B21: ='Budget Plan'!A76 -> Net Profit | C21: =SUM('Budget Plan'!G76:R76) -> #REF! | D21: =SUM('Budget Plan'!S76:AD76) -> #REF! | E21: =SUM('Budget Plan'!AE76:AP76) -> #REF! | F21: =SUM(C21:E21) -> #REF! | G21: =F21/$F$9 -> #REF!
B22: RE | C22: ='Budget Plan'!R77 -> #REF! | D22: ='Budget Plan'!AD77 -> #REF! | E22: ='Budget Plan'!AP77 -> #REF! | F22: =SUM(C22:E22) -> #REF!
B24: Cash Flow | C24: Year 1 | D24: Year 2 | E24: Year 3 | F24: Total | G24: %
B25: Cash In | C25: =SUM(C26:C27) -> 0 | D25: =SUM(D26:D27) -> 0 | E25: =SUM(E26:E27) -> 0 | F25: =SUM(C25:E25) -> 0 | G25: =F25/$F$25 -> #DIV/0!
B26: Develop for INET | C26: =SUM('Budget Plan'!G80:R80) -> 0 | D26: =SUM('Budget Plan'!H80:S80) -> 0 | E26: =SUM('Budget Plan'!I80:T80) -> 0 | F26: =SUM(C26:E26) -> 0 | G26: =F26/$F$25 -> #DIV/0!
B27: Revenue from customer | C27: =SUM('Budget Plan'!G81:R82) -> 0 | D27: =SUM('Budget Plan'!S81:AD82) -> 0 | E27: =SUM('Budget Plan'!AE81:AP82) -> 0 | F27: =SUM(C27:E27) -> 0 | G27: =F27/$F$25 -> #DIV/0!
B28: Cash Out | C28: =SUM(C29,C32:C33) -> #REF! | D28: =SUM(D29,D32:D33) -> #REF! | E28: =SUM(E29,E32:E33) -> #REF! | F28: =SUM(C28:E28) -> #REF! | G28: =F28/$F$25 -> #REF!
B29: ='Budget Plan'!A84 -> Direct Cost | C29: =SUM(C30:C31) -> 0 | D29: =SUM(D30:D31) -> 0 | E29: =SUM(E30:E31) -> 0 | F29: =SUM(C29:E29) -> 0 | G29: =F29/$F$25 -> #DIV/0!
B30: ='Budget Plan'!A85 -> One Time | C30: =SUM('Budget Plan'!G85:R85) -> 0 | D30: =SUM('Budget Plan'!S85:AD85) -> 0 | E30: =SUM('Budget Plan'!AE85:AP85) -> 0 | F30: =SUM(C30:E30) -> 0 | G30: =F30/$F$25 -> #DIV/0!
B31: ='Budget Plan'!A88 -> Recurring | C31: =SUM('Budget Plan'!G88:R88) -> 0 | D31: =SUM('Budget Plan'!S88:AD88) -> 0 | E31: =SUM('Budget Plan'!AE88:AP88) -> 0 | F31: =SUM(C31:E31) -> 0 | G31: =F31/$F$25 -> #DIV/0!
B32: ='Budget Plan'!A92 -> Revshare | C32: =SUM('Budget Plan'!G92:R92) -> 0 | D32: =SUM('Budget Plan'!S92:AD92) -> 0 | E32: =SUM('Budget Plan'!AE92:AP92) -> 0 | F32: =SUM(C32:E32) -> 0 | G32: =F32/$F$25 -> #DIV/0!
B33: ='Budget Plan'!A93 -> SG&A | C33: =SUM(C34:C34) -> #REF! | D33: =SUM(D34:D34) -> #REF! | E33: =SUM(E34:E34) -> #REF! | F33: =SUM(C33:E33) -> #REF! | G33: =F33/$F$25 -> #REF!
B34: Sale & Management | C34: =SUM('Budget Plan'!G93:R93) -> #REF! | D34: =SUM('Budget Plan'!S93:AD93) -> #REF! | E34: =SUM('Budget Plan'!AE93:AP93) -> #REF! | F34: =SUM(C34:E34) -> #REF! | G34: =F34/$F$25 -> #REF!
B35: ='Budget Plan'!A96 -> Net Cash | C35: =SUM('Budget Plan'!G96:R96) -> #REF! | D35: =SUM('Budget Plan'!S96:AD96) -> #REF! | E35: =SUM('Budget Plan'!AE96:AP96) -> #REF! | F35: =SUM(C35:E35) -> #REF! | G35: =F35/$F$25 -> #REF!
B36: Cash CF | C36: ='Budget Plan'!R98 -> #REF! | D36: ='Budget Plan'!AD98 -> #REF! | E36: ='Budget Plan'!AP98 -> #REF! | F36: =SUM(C36:E36) -> #REF!

Sheet BOM 4 vm 99.90% Disk SSD
C1: เอกสารสนับสนุน (แบบฟอร์ม) | F1: หน่วยงาน : ส่วนงานบริหารต้นทุนองค์กร | H1: version 1.0 | I1: วันที่บังคับใช้ : 09/05/2016
C2: หัวข้อ : BOM (Bill of Material) Cost | F2: FM-BOM Cost | H2: ผู้อนุมัติ : | I2: หรรษา นวาระพรรณ | J2: หน้า : 1/1
B3: Cost Project :MBKC
B4: Sale : Pimpan Deachapiyamit
B5: Pre-sale : Vatcharapong Tavichai | F5: Actual Cost | G5: =G35 -> #REF! | H5: Eng. Cost/Year | I5: =I35 -> #REF!
B6: Date : 17/02/2017
B7: Version : 6
B8: Cost By : Supawadee
D9: Contract | E9: 2 | F9: Month | I9: 0.8
A10: Vendor | B10: =B3 -> Cost Project :MBKC | C10: Unit | E10: Unit/Price | F10: Price | G10: Actual Cost | I10: Eng. Cost | J10: Eng. Cost/Month
B11: One Time Charge
B12: Manage Service By Project Team | C12: 0 | F12: =C12*E12 -> 0 | G12: =F12*$E$9 -> 0 | H12: =G12/$G$5 -> #REF! | I12: =G12/$I$9 -> 0 | J12: =I12/$E$9 -> 0
B13: Implement PHP&Apache by Project Team | C13: 0 | D13: VM | E13: =5000*0.8 -> 4000 | F13: =C13*E13 -> 0 | G13: =F13 -> 0 | H13: =G13/$G$5 -> #REF! | I13: =G13/$I$9 -> 0 | J13: =I13/$E$9 -> 0
B15: ToTal
B16: Recurring
B17: MsCloud (VDC) | C17: 0 | F17: =C17*E17 -> 0 | G17: =F17*$E$9 -> 0 | H17: =G17/$G$5 -> #REF! | I17: =G17/$I$9 -> 0 | J17: =I17/$E$9 -> 0
A18: INET | B18: VCPU(GHz) | C18: =#REF! -> #REF! | D18: GHz | E18: =105*0.8 -> 84 | F18: =C18*E18 -> #REF! | G18: =F18*$E$9 -> #REF! | H18: =G18/$G$5 -> #REF! | I18: =G18/$I$9 -> #REF! | J18: =I18/$E$9 -> #REF!
A19: INET | B19: Vram(GB) | C19: =#REF! -> #REF! | D19: GB | E19: =100*0.8 -> 80 | F19: =C19*E19 -> #REF! | G19: =F19*$E$9 -> #REF! | H19: =G19/$G$5 -> #REF! | I19: =G19/$I$9 -> #REF! | J19: =I19/$E$9 -> #REF!
A20: INET | B20: VDisk (SSD) +Backup snapshot 4 copy & Snapmirror 7 copy | C20: =#REF! -> #REF! | D20: GB | E20: =3*0.8 -> 2.4 | F20: =C20*E20 -> #REF! | G20: =F20*$E$9 -> #REF! | H20: =G20/$G$5 -> #REF! | I20: =G20/$I$9 -> #REF! | J20: =I20/$E$9 -> #REF!
A21: INET | B21: VDisk (Hybrid) add on RTO/RPO 4 hr. | C21: =C20*4*0 -> #REF! | D21: GB | E21: =2.8*0.8 -> 2.24 | F21: =C21*E21 -> #REF! | G21: =F21*$E$9 -> #REF! | H21: =G21/$G$5 -> #REF! | I21: =G21/$I$9 -> #REF! | J21: =I21/$E$9 -> #REF!
A22: INET | B22: Cost B/W(follow VM) | C22: 2 | D22: VM | E22: =300*0.8 -> 240 | F22: =C22*E22 -> 480 | G22: =F22*$E$9 -> 960 | H22: =G22/$G$5 -> #REF! | I22: =G22/$I$9 -> 1200 | J22: =I22/$E$9 -> 600
A23: INET | B23: IP Address(follow VM) | C23: 2 | D23: IP | E23: =80*0.8 -> 64 | F23: =C23*E23 -> 128 | G23: =F23*$E$9 -> 256 | H23: =G23/$G$5 -> #REF! | I23: =G23/$I$9 -> 320 | J23: =I23/$E$9 -> 160
A24: INET | B24: Monitoring& Alert(follow VM) | C24: 2 | D24: Vm | E24: =150*0.8 -> 120 | F24: =C24*E24 -> 240 | G24: =F24*$E$9 -> 480 | H24: =G24/$G$5 -> #REF! | I24: =G24/$I$9 -> 600 | J24: =I24/$E$9 -> 300
A25: INET | B25: Antivirus(follow VM) | C25: 2 | D25: Vm | E25: =150*0.8 -> 120 | F25: =C25*E25 -> 240 | G25: =F25*$E$9 -> 480 | H25: =G25/$G$5 -> #REF! | I25: =G25/$I$9 -> 600 | J25: =I25/$E$9 -> 300
A26: INET | B26: Operation Cost(follow VM) | C26: 2 | D26: Vm | E26: =200*0.8 -> 160 | F26: =C26*E26 -> 320 | G26: =F26*$E$9 -> 640 | H26: =G26/$G$5 -> #REF! | I26: =G26/$I$9 -> 800 | J26: =I26/$E$9 -> 400
A27: INET | B27: SQL License Std. /2 vcpu | D27: License | E27: =510*0.8 -> 408 | F27: =C27*E27 -> 0 | G27: =F27*$E$9 -> 0 | H27: =G27/$G$5 -> #REF! | I27: =G27/$I$9 -> 0 | J27: =I27/$E$9 -> 0
B28: Security By Project Team | C28: 0 | F28: =C28*E28 -> 0 | G28: =F28*$E$9 -> 0 | H28: =G28/$G$5 -> #REF! | I28: =G28/$I$9 -> 0 | J28: =I28/$E$9 -> 0
A29: INET | B29: Virtual Firewall Force point + VPN 10 Accounts + Policy 300 Policy | C29: 1 | D29: Unit | E29: =8000*0.8 -> 6400 | F29: =C29*E29 -> 6400 | G29: =F29*$E$9 -> 12800 | H29: =G29/$G$5 -> #REF! | I29: =G29/$I$9 -> 16000 | J29: =I29/$E$9 -> 8000
B30: Manage Service By Project Team | C30: 0 | F30: =C30*E30 -> 0 | G30: =F30*$E$9 -> 0 | H30: =G30/$G$5 -> #REF! | I30: =G30/$I$9 -> 0 | J30: =I30/$E$9 -> 0
A31: Project | B31: Manage Service (Monitoring) | C31: 2 | D31: Vm | E31: =1000*0.8 -> 800 | F31: =C31*E31 -> 1600 | G31: =F31*$E$9 -> 3200 | H31: =G31/$G$5 -> #REF! | I31: =G31/$I$9 -> 4000 | J31: =I31/$E$9 -> 2000
A32: Project | B32: DBA MYSQL for 1 VM (Advance Scope) | C32: 0 | D32: VM | E32: =15000*0.8 -> 12000 | F32: =C32*E32 -> 0 | G32: =F32*$E$9 -> 0 | H32: =G32/$G$5 -> #REF! | I32: =G32/$I$9 -> 0 | J32: =I32/$E$9 -> 0
B33: Add-On | E33: 0 | F33: =C33*E33 -> 0 | G33: =F33*$E$9 -> 0 | H33: =G33/$G$5 -> #REF! | I33: =G33/$I$9 -> 0 | J33: =I33/$E$9 -> 0
A34: Vendor | B34: Innitial setup c panel & support หลังงานติดตั้ง 24x7 | C34: 1 | D34: unit | F34: =C34*E34 -> 0 | G34: =F34*$E$9 -> 0 | H34: =G34/$G$5 -> #REF! | I34: =G34/$I$9 -> 0 | J34: =I34/$E$9 -> 0
B35: Grand Total | G35: =SUM(G11:G34) -> #REF! | H35: =G35/$G$5 -> #REF! | I35: =SUM(I11:I34) -> #REF! | J35: =SUM(J11:J34) -> #REF!
B36: Total Cost | C36: =E9 -> 2 | D36: Month | F36: =I35 -> #REF!
B37: Cost per Month | C37: 1 | D37: =D36 -> Month | F37: =F36/C36 -> #REF!
B38: Sale | F38: =F37*0.9 -> #REF!
B39: Sale Factor | F39: =F38/F37 -> #REF!
B41: Remark :
B42: throughput vFW เป็น estinmate
B43: SLA 99.90 RTO/RPO 4 hr.
B44: INET ดูแลแค่ส่วนของ Osและ DBA ตาม standard scope
B46: ***ไม่รวมดูแล applicaton&service ทางลูกค้าดูแลเอง
B48: config c panel ของ web manage ให้ทาง sale คุยกับทาง partner ก่อน

Sheet Diagram-99.90%
E1: เอกสารสนับสนุน (แบบฟอร์ม) | H1: หน่วยงาน : ส่วนงานบริหารต้นทุนองค์กร | L1: version 1.0 | O1: วันที่บังคับใช้ : 09/05/2016
E2: หัวข้อ : BOM (Bill of Material) Cost | I2: FM-BOM Cost | L2: ผู้อนุมัติ : | M2: หรรษา นวาระพรรณ | Q2: หน้า : 1/1
B3: Project Solution
B4: Project :
B5: Create by :
B6: Approved by :
B7: Version :
B8: Solution Diagram
G10: Capture figure diagram
G11: (ใส่รูปภาพที่ได้นำเสนอและตกลงร่วมกับลูกค้า)
B19: อธิบาย Solution [อ้างอิงตาม Diagram]

Sheet Cost Managed service
L12: 25000
L14: 15000
